MeuProjeto/mux1x2.vhd
library IEEE;
use IEEE.std_logic_1164.all;
use IEEE.numeric_std.all;

entity mux1x2 is
    port(
        slt: in std_logic;
        in0,in1: in signed(15 downto 0);
        
        out0:out signed(15 downto 0)
    );
end entity mux1x2;

architecture a_mux1x2 of mux1x2 is
    
begin

    out0<= in0 when slt='0' else
            in1 when slt='1' else
            "0000000000000000";

end architecture a_mux1x2;

MeuProjeto/reg16bit.vhd
library IEEE;
use IEEE.std_logic_1164.all;
use IEEE.numeric_std.all;

entity reg16bit is
    port(
        clk :in std_logic;
        rst :in std_logic;
        wr_en: in std_logic;
        data_in: in signed(15 downto 0);
        data_out: out signed(15 downto 0)
    );
end entity reg16bit;

architecture a_reg16bit of reg16bit is
    signal registro: signed(15 downto 0);
begin

   process (clk,rst,wr_en)
   begin
       if rst='1' then
           registro<="0000000000000000";
       elsif wr_en='1' then
           if rising_edge(clk) then
               registro<=data_in;
           end if;
       end if;
   end process;
   
   data_out <= registro;

end architecture a_reg16bit;

MeuProjeto/bancoreg.vhd
library IEEE;
use IEEE.std_logic_1164.all;
use IEEE.numeric_std.all;

entity bancoreg is
    port(
        slt_read1: in unsigned(2 downto 0);
        slt_read2: in unsigned(2 downto 0);
        dados_write: in signed(15 downto 0);
        slt_write: in unsigned(2 downto 0);
        wr_en: in STD_LOGIC;
        clk: in STD_LOGIC;
        rst: in STD_LOGIC;
        
        dados_read1: out signed(15 downto 0);
        dados_read2: out signed(15 downto 0)
    );
end entity bancoreg;

architecture a_bancoreg of bancoreg is
    component reg16bit is
        port
        (
            clk      : IN std_logic ;
            rst      : IN std_logic ;
            wr_en    : IN std_logic ;
            data_in  : IN signed (15 downto 0);
            data_out : OUT signed (15 downto 0)
        );
    end component;
    
    signal wr_en1,wr_en2,wr_en3,wr_en4,wr_en5,wr_en6,wr_en7: STD_LOGIC :='0';
    signal data_out0,data_out1,data_out2,data_out3,data_out4,data_out5,data_out6,data_out7: signed(15 downto 0);
    constant wr_en0:STD_LOGIC:='0';
    
begin

    reg0: reg16bit port map(clk=>clk, rst=>rst, wr_en=>wr_en0, data_in=>dados_write, data_out=>data_out0);
    reg1: reg16bit port map(clk=>clk, rst=>rst, wr_en=>wr_en1, data_in=>dados_write, data_out=>data_out1);
    reg2: reg16bit port map(clk=>clk, rst=>rst, wr_en=>wr_en2, data_in=>dados_write, data_out=>data_out2);
    reg3: reg16bit port map(clk=>clk, rst=>rst, wr_en=>wr_en3, data_in=>dados_write, data_out=>data_out3);
    reg4: reg16bit port map(clk=>clk, rst=>rst, wr_en=>wr_en4, data_in=>dados_write, data_out=>data_out4);
    reg5: reg16bit port map(clk=>clk, rst=>rst, wr_en=>wr_en5, data_in=>dados_write, data_out=>data_out5);
    reg6: reg16bit port map(clk=>clk, rst=>rst, wr_en=>wr_en6, data_in=>dados_write, data_out=>data_out6);
    reg7: reg16bit port map(clk=>clk, rst=>rst, wr_en=>wr_en7, data_in=>dados_write, data_out=>data_out7);
    
    wr_en1<='1' when slt_write = "001" else '0';
    wr_en2<='1' when slt_write = "010" else '0';
    wr_en3<='1' when slt_write = "011" else '0';
    wr_en4<='1' when slt_write = "100" else '0';
    wr_en5<='1' when slt_write = "101" else '0';
    wr_en6<='1' when slt_write = "110" else '0';
    wr_en7<='1' when slt_write = "111" else '0';
    
    dados_read1 <= data_out0 when slt_read1 ="000" else
                    data_out1 when slt_read1 ="001" else
                    data_out2 when slt_read1 ="010" else
                    data_out3 when slt_read1 ="011" else
                    data_out4 when slt_read1 ="100" else
                    data_out5 when slt_read1 ="101" else
                    data_out6 when slt_read1 ="110" else
                    data_out7 when slt_read1 ="111" else
                    "0000000000000000";
    
    dados_read2 <= data_out0 when slt_read2 ="000" else
                    data_out1 when slt_read2 ="001" else
                    data_out2 when slt_read2 ="010" else
                    data_out3 when slt_read2 ="011" else
                    data_out4 when slt_read2 ="100" else
                    data_out5 when slt_read2 ="101" else
                    data_out6 when slt_read2 ="110" else
                    data_out7 when slt_read2 ="111" else
                    "0000000000000000";

end architecture a_bancoreg;

MeuProjeto/ULA.vhd
--Alunos: Jhonny Kristyan Vaz-Tostes de Assis
--        Gabriel Henrique Kwiatkovski Godinho
-- entrega ULA

library ieee;
use ieee.std_logic_1164.all;
use ieee.numeric_std.all;

--------------------
-- 00 = soma
-- 01 = subtração
-- 10 = maior
-- 11 = diferente
--------------------

entity ULA is 
    port(   in_termo_1 : in signed (15 downto 0);
            in_termo_2 : in signed (15 downto 0);

            select_op : in unsigned(1 downto 0);

            out_op_1 : out signed (15 downto 0);
            out_op_2 : out std_logic);
end entity;

architecture a_ULA of ULA is
    signal in_1_17, in_2_17, soma_17: signed(16 downto 0);
begin
    in_1_17 <= '0' & in_termo_1;
    in_2_17 <= '0' & in_termo_2;
    soma_17 <= in_termo_1 + in_2_17;
    
    out_op_1 <= in_termo_1+in_termo_2 when select_op="00" else
                in_termo_2-in_termo_1 when select_op="01" else
                "0000000000000000";

    out_op_2 <= soma_17(1) when select_op="00" else
                '1' when select_op="01" and in_termo_1 > in_termo_2 else
                '1' when select_op="10" and (in_termo_1 > in_termo_2) else
                '1' when select_op="11" and (in_termo_1 /= in_termo_2) else
                '0';

end architecture;

--------------------------------------------------

MeuProjeto/gerenciador.vhd
library IEEE;
use IEEE.std_logic_1164.all;
use IEEE.numeric_std.all;

entity gerenciador is
    port(
        top_level: in signed(15 downto 0);
        clk,rst,wr_en: in STD_LOGIC;
        
        slt_ula: in unsigned(1 downto 0);
        slt_reg_read_1, slt_reg_read_2, slt_reg_write: in unsigned(2 downto 0);
        ALUsrc: in std_logic;
        
        debug_top_level: out signed(15 downto 0)
    );
end entity gerenciador;

architecture a_gerenciador of gerenciador is
    component ULA is
        port
        (
            in_termo_1  : IN signed (15 downto 0);
            in_termo_2  : IN signed (15 downto 0);
            select_op   : IN unsigned(1 downto 0);
            out_op_1    : OUT signed (15 downto 0);
            out_op_2    : OUT std_logic
        );
    end component;
    
    component bancoreg is
        port
        (
            slt_read1   : IN unsigned (2 downto 0);
            slt_read2   : IN unsigned (2 downto 0);
            dados_write : IN signed (15 downto 0);
            slt_write   : IN unsigned (2 downto 0);
            wr_en       : IN STD_LOGIC ;
            clk         : IN STD_LOGIC ;
            rst         : IN STD_LOGIC ;
            dados_read1 : OUT signed (15 downto 0);
            dados_read2 : OUT signed (15 downto 0)
        );
    end component;
    
    component mux1x2 is
        port
        (
            slt  : IN std_logic;
            in0  : IN signed (15 downto 0);
            in1  : IN signed (15 downto 0);
            out0 : OUT signed (15 downto 0)
        );
    end component;
    
    signal out_banco_1,out_banco_2,out_mux,out_ULA: signed(15 downto 0);
    signal out_ULA_2: STD_LOGIC;
    
begin
    ULA1 : ULA port map(
        in_termo_1=>out_banco_1, 
        in_termo_2=>out_mux,
        select_op=>slt_ula, 
        out_op_1=>out_ULA, 
        out_op_2=>out_ULA_2 
    );
    
    banco: bancoreg port map(
        slt_read1=>slt_reg_read_1, 
        slt_read2=>slt_reg_read_2, 
        dados_write=>out_ULA, 
        slt_write=>slt_reg_write, 
        wr_en=>wr_en, 
        clk=>clk, 
        rst=>rst, 
        dados_read1=>out_banco_1, 
        dados_read2=>out_banco_2
    );
    
    mux: mux1x2 port map(
        slt=>ALUsrc, 
        in0=>out_banco_2, 
        in1=>top_level, 
    
        out0=>out_mux
    );
    
    debug_top_level<=out_ULA;


end architecture a_gerenciador;

MeuProjeto/gerenciador_tb.vhd
library IEEE;
use IEEE.std_logic_1164.all;
use IEEE.numeric_std.all;

entity gerenciador_tb is
end entity gerenciador_tb;

architecture a_gerenciador_tb of gerenciador_tb is
    component gerenciador is
        port
        (
            top_level       : IN signed (15 downto 0);
            clk             : IN STD_LOGIC ;
            rst             : IN STD_LOGIC ;
            wr_en           : IN STD_LOGIC ;
            slt_ula         : IN unsigned (1 downto 0);
            slt_reg_read_1  : IN unsigned (2 downto 0);
            slt_reg_read_2  : IN unsigned (2 downto 0);
            slt_reg_write   : IN unsigned (2 downto 0);
            ALUsrc          : IN std_logic; 
            debug_top_level : OUT signed (15 downto 0)
        );
    end component;


    constant period_time : time := 100 ns;
    signal finished : std_logic := '0';
    signal clk, reset : std_logic;

    signal top_level, debug_top_level :signed (15 downto 0):="0000000000000000";
    signal wr_en, ALUsrc: std_logic:='0';
    signal slt_ula : unsigned (1 downto 0):="00";
    signal slt_reg_read_1, slt_reg_read_2, slt_reg_write :  unsigned (2 downto 0):="000";



begin

    uut: gerenciador port map(  top_level=>top_level,
                                clk=>clk,
                                rst=>reset,
                                wr_en=>wr_en,
                                slt_ula=>slt_ula,
                                slt_reg_read_1=>slt_reg_read_1,
                                slt_reg_read_2=>slt_reg_read_2,
                                slt_reg_write=>slt_reg_write,
                                ALUsrc=>ALUsrc,
                                debug_top_level=>debug_top_level);

--TESTES

    reset_global: process
    begin
        reset <= '1';
        wait for period_time*2; -- espera 2 clocks, pra garantir
        reset <= '0';
        wait;
    end process;
  
    sim_time_proc: process
    begin
        wait for 3000 ns;
        finished <= '1';
        wait;
    end process sim_time_proc;

    clk_proc: process
    begin -- gera clock até que sim_time_proc termine
        while finished /= '1' loop
        clk <= '0';
        wait for period_time/2;
        clk <= '1';
        wait for period_time/2;
        end loop;
        wait;
    end process clk_proc;  
    
    process 
    begin
        --addi $1,$0,3
        wait for 200 ns;
        top_level <= "0000000000000011";
        slt_reg_write <= "001";
        wr_en <= '1';
        ALUsrc <= '1';
        slt_reg_read_1 <= "000";
        slt_ula <= "00";
      
        --addi $4,$0,4
        wait for 100 ns;
        top_level <= "0000000000000100";
        slt_reg_write <= "100";
       
        --add $5,$1,$4
        wait for 100 ns;
        ALUsrc <= '0';
        slt_reg_read_1 <= "001";
        slt_reg_read_2 <= "100";
        slt_reg_write <= "101";
       
        --addi $6,$0,2
        wait for 100 ns;
        ALUsrc <= '1';
        top_level <= "0000000000000010";
        slt_reg_write <= "110";
        slt_reg_read_1 <= "000";

        --sub $1,$5,$6
        wait for 100 ns;
        slt_ula <= "01";
        ALUsrc <= '0';
        slt_reg_read_1 <= "110";
        slt_reg_read_2 <= "101";
        slt_reg_write <= "001";
        wait for 100 ns;


        wr_en <= '0';
        wait;
    end process;
end architecture a_gerenciador_tb;

MeuProjeto/gerenciador_tb.vcd
$date
  Thu Nov 25 17:01:06 2021
$end
$version
  GHDL v0
$end
$timescale
  1 fs
$end
$scope module standard $end
$upscope $end
$scope module textio $end
$upscope $end
$scope module std_logic_1164 $end
$upscope $end
$scope module numeric_std $end
$upscope $end
$scope module gerenciador_tb $end
$var reg 1 ! finished $end
$var reg 1 " clk $end
$var reg 1 # reset $end
$var reg 16 $ top_level[15:0] $end
$var reg 16 % debug_top_level[15:0] $end
$var reg 1 & wr_en $end
$var reg 1 ' alusrc $end
$var reg 2 ( slt_ula[1:0] $end
$var reg 3 ) slt_reg_read_1[2:0] $end
$var reg 3 * slt_reg_read_2[2:0] $end
$var reg 3 + slt_reg_write[2:0] $end
$scope module uut $end
$var reg 16 , top_level[15:0] $end
$var reg 1 - clk $end
$var reg 1 . rst $end
$var reg 1 / wr_en $end
$var reg 2 0 slt_ula[1:0] $end
$var reg 3 1 slt_reg_read_1[2:0] $end
$var reg 3 2 slt_reg_read_2[2:0] $end
$var reg 3 3 slt_reg_write[2:0] $end
$var reg 1 4 alusrc $end
$var reg 16 5 debug_top_level[15:0] $end
$var reg 16 6 out_banco_1[15:0] $end
$var reg 16 7 out_banco_2[15:0] $end
$var reg 16 8 out_mux[15:0] $end
$var reg 16 9 out_ula[15:0] $end
$var reg 1 : out_ula_2 $end
$scope module ula1 $end
$var reg 16 ; in_termo_1[15:0] $end
$var reg 16 < in_termo_2[15:0] $end
$var reg 2 = select_op[1:0] $end
$var reg 16 > out_op_1[15:0] $end
$var reg 1 ? out_op_2 $end
$var reg 17 @ in_1_17[16:0] $end
$var reg 17 A in_2_17[16:0] $end
$var reg 17 B soma_17[16:0] $end
$upscope $end
$scope module banco $end
$var reg 3 C slt_read1[2:0] $end
$var reg 3 D slt_read2[2:0] $end
$var reg 16 E dados_write[15:0] $end
$var reg 3 F slt_write[2:0] $end
$var reg 1 G wr_en $end
$var reg 1 H clk $end
$var reg 1 I rst $end
$var reg 16 J dados_read1[15:0] $end
$var reg 16 K dados_read2[15:0] $end
$var reg 1 L wr_en1 $end
$var reg 1 M wr_en2 $end
$var reg 1 N wr_en3 $end
$var reg 1 O wr_en4 $end
$var reg 1 P wr_en5 $end
$var reg 1 Q wr_en6 $end
$var reg 1 R wr_en7 $end
$var reg 16 S data_out0[15:0] $end
$var reg 16 T data_out1[15:0] $end
$var reg 16 U data_out2[15:0] $end
$var reg 16 V data_out3[15:0] $end
$var reg 16 W data_out4[15:0] $end
$var reg 16 X data_out5[15:0] $end
$var reg 16 Y data_out6[15:0] $end
$var reg 16 Z data_out7[15:0] $end
$scope module reg0 $end
$var reg 1 [ clk $end
$var reg 1 \ rst $end
$var reg 1 ] wr_en $end
$var reg 16 ^ data_in[15:0] $end
$var reg 16 _ data_out[15:0] $end
$var reg 16 ` registro[15:0] $end
$upscope $end
$scope module reg1 $end
$var reg 1 a clk $end
$var reg 1 b rst $end
$var reg 1 c wr_en $end
$var reg 16 d data_in[15:0] $end
$var reg 16 e data_out[15:0] $end
$var reg 16 f registro[15:0] $end
$upscope $end
$scope module reg2 $end
$var reg 1 g clk $end
$var reg 1 h rst $end
$var reg 1 i wr_en $end
$var reg 16 j data_in[15:0] $end
$var reg 16 k data_out[15:0] $end
$var reg 16 l registro[15:0] $end
$upscope $end
$scope module reg3 $end
$var reg 1 m clk $end
$var reg 1 n rst $end
$var reg 1 o wr_en $end
$var reg 16 p data_in[15:0] $end
$var reg 16 q data_out[15:0] $end
$var reg 16 r registro[15:0] $end
$upscope $end
$scope module reg4 $end
$var reg 1 s clk $end
$var reg 1 t rst $end
$var reg 1 u wr_en $end
$var reg 16 v data_in[15:0] $end
$var reg 16 w data_out[15:0] $end
$var reg 16 x registro[15:0] $end
$upscope $end
$scope module reg5 $end
$var reg 1 y clk $end
$var reg 1 z rst $end
$var reg 1 { wr_en $end
$var reg 16 | data_in[15:0] $end
$var reg 16 } data_out[15:0] $end
$var reg 16 !" registro[15:0] $end
$upscope $end
$scope module reg6 $end
$var reg 1 "" clk $end
$var reg 1 #" rst $end
$var reg 1 $" wr_en $end
$var reg 16 %" data_in[15:0] $end
$var reg 16 &" data_out[15:0] $end
$var reg 16 '" registro[15:0] $end
$upscope $end
$scope module reg7 $end
$var reg 1 (" clk $end
$var reg 1 )" rst $end
$var reg 1 *" wr_en $end
$var reg 16 +" data_in[15:0] $end
$var reg 16 ," data_out[15:0] $end
$var reg 16 -" registro[15:0] $end
$upscope $end
$upscope $end
$scope module mux $end
$var reg 1 ." slt $end
$var reg 16 /" in0[15:0] $end
$var reg 16 0" in1[15:0] $end
$var reg 16 1" out0[15:0] $end
$upscope $end
$upscope $end
$upscope $end
$enddefinitions $end
#0
0!
0"
1#
b0000000000000000 $
b0000000000000000 %
0&
0'
b00 (
b000 )
b000 *
b000 +
b0000000000000000 ,
0-
1.
0/
b00 0
b000 1
b000 2
b000 3
04
b0000000000000000 5
b0000000000000000 6
b0000000000000000 7
b0000000000000000 8
b0000000000000000 9
0:
b0000000000000000 ;
b0000000000000000 <
b00 =
b0000000000000000 >
0?
b00000000000000000 @
b00000000000000000 A
b00000000000000000 B
b000 C
b000 D
b0000000000000000 E
b000 F
0G
0H
1I
b0000000000000000 J
b0000000000000000 K
0L
0M
0N
0O
0P
0Q
0R
b0000000000000000 S
b0000000000000000 T
b0000000000000000 U
b0000000000000000 V
b0000000000000000 W
b0000000000000000 X
b0000000000000000 Y
b0000000000000000 Z
0[
1\
0]
b0000000000000000 ^
b0000000000000000 _
b0000000000000000 `
0a
1b
0c
b0000000000000000 d
b0000000000000000 e
b0000000000000000 f
0g
1h
0i
b0000000000000000 j
b0000000000000000 k
b0000000000000000 l
0m
1n
0o
b0000000000000000 p
b0000000000000000 q
b0000000000000000 r
0s
1t
0u
b0000000000000000 v
b0000000000000000 w
b0000000000000000 x
0y
1z
0{
b0000000000000000 |
b0000000000000000 }
b0000000000000000 !"
0""
1#"
0$"
b0000000000000000 %"
b0000000000000000 &"
b0000000000000000 '"
0("
1)"
0*"
b0000000000000000 +"
b0000000000000000 ,"
b0000000000000000 -"
0."
b0000000000000000 /"
b0000000000000000 0"
b0000000000000000 1"
#50000000
1"
1-
1H
1[
1a
1g
1m
1s
1y
1""
1("
#100000000
0"
0-
0H
0[
0a
0g
0m
0s
0y
0""
0("
#150000000
1"
1-
1H
1[
1a
1g
1m
1s
1y
1""
1("
#200000000
0"
0#
b0000000000000011 $
b0000000000000011 %
1&
1'
b001 +
b0000000000000011 ,
0-
0.
1/
b001 3
14
b0000000000000011 5
b0000000000000011 8
b0000000000000011 9
1:
b0000000000000011 <
b0000000000000011 >
1?
b00000000000000011 A
b00000000000000011 B
b0000000000000011 E
b001 F
1G
0H
0I
1L
0[
0\
b0000000000000011 ^
0a
0b
1c
b0000000000000011 d
0g
0h
b0000000000000011 j
0m
0n
b0000000000000011 p
0s
0t
b0000000000000011 v
0y
0z
b0000000000000011 |
0""
0#"
b0000000000000011 %"
0("
0)"
b0000000000000011 +"
1."
b0000000000000011 0"
b0000000000000011 1"
#250000000
1"
1-
1H
b0000000000000011 T
1[
1a
b0000000000000011 e
b0000000000000011 f
1g
1m
1s
1y
1""
1("
#300000000
0"
b0000000000000100 $
b0000000000000100 %
b100 +
b0000000000000100 ,
0-
b100 3
b0000000000000100 5
b0000000000000100 8
b0000000000000100 9
0:
b0000000000000100 <
b0000000000000100 >
0?
b00000000000000100 A
b00000000000000100 B
b0000000000000100 E
b100 F
0H
0L
1O
0[
b0000000000000100 ^
0a
0c
b0000000000000100 d
0g
b0000000000000100 j
0m
b0000000000000100 p
0s
1u
b0000000000000100 v
0y
b0000000000000100 |
0""
b0000000000000100 %"
0("
b0000000000000100 +"
b0000000000000100 0"
b0000000000000100 1"
#350000000
1"
1-
1H
b0000000000000100 W
1[
1a
1g
1m
1s
b0000000000000100 w
b0000000000000100 x
1y
1""
1("
#400000000
0"
b0000000000000111 %
0'
b001 )
b100 *
b101 +
0-
b001 1
b100 2
b101 3
04
b0000000000000111 5
b0000000000000011 6
b0000000000000100 7
b0000000000000100 8
b0000000000000111 9
1:
b0000000000000011 ;
b0000000000000100 <
b0000000000000111 >
1?
b00000000000000011 @
b00000000000000100 A
b00000000000000111 B
b001 C
b100 D
b0000000000000111 E
b101 F
0H
b0000000000000011 J
b0000000000000100 K
0O
1P
0[
b0000000000000111 ^
0a
b0000000000000111 d
0g
b0000000000000111 j
0m
b0000000000000111 p
0s
0u
b0000000000000111 v
0y
1{
b0000000000000111 |
0""
b0000000000000111 %"
0("
b0000000000000111 +"
0."
b0000000000000100 /"
b0000000000000100 1"
#450000000
1"
1-
1H
b0000000000000111 X
1[
1a
1g
1m
1s
1y
b0000000000000111 }
b0000000000000111 !"
1""
1("
#500000000
0"
b0000000000000010 $
b0000000000000010 %
1'
b000 )
b110 +
b0000000000000010 ,
0-
b000 1
b110 3
14
b0000000000000010 5
b0000000000000000 6
b0000000000000010 8
b0000000000000010 9
1:
b0000000000000000 ;
b0000000000000010 <
b0000000000000010 >
1?
b00000000000000000 @
b00000000000000010 A
b00000000000000010 B
b000 C
b0000000000000010 E
b110 F
0H
b0000000000000000 J
0P
1Q
0[
b0000000000000010 ^
0a
b0000000000000010 d
0g
b0000000000000010 j
0m
b0000000000000010 p
0s
b0000000000000010 v
0y
0{
b0000000000000010 |
0""
1$"
b0000000000000010 %"
0("
b0000000000000010 +"
1."
b0000000000000010 0"
b0000000000000010 1"
#550000000
1"
1-
1H
b0000000000000010 Y
1[
1a
1g
1m
1s
1y
1""
b0000000000000010 &"
b0000000000000010 '"
1("
#600000000
0"
b0000000000000101 %
0'
b01 (
b110 )
b101 *
b001 +
0-
b01 0
b110 1
b101 2
b001 3
04
b0000000000000101 5
b0000000000000010 6
b0000000000000111 7
b0000000000000111 8
b0000000000000101 9
0:
b0000000000000010 ;
b0000000000000111 <
b01 =
b0000000000000101 >
0?
b00000000000000010 @
b00000000000000111 A
b00000000000001001 B
b110 C
b101 D
b0000000000000101 E
b001 F
0H
b0000000000000010 J
b0000000000000111 K
1L
0Q
0[
b0000000000000101 ^
0a
1c
b0000000000000101 d
0g
b0000000000000101 j
0m
b0000000000000101 p
0s
b0000000000000101 v
0y
b0000000000000101 |
0""
0$"
b0000000000000101 %"
0("
b0000000000000101 +"
0."
b0000000000000111 /"
b0000000000000111 1"
#650000000
1"
1-
1H
b0000000000000101 T
1[
1a
b0000000000000101 e
b0000000000000101 f
1g
1m
1s
1y
1""
1("
#700000000
0"
0&
0-
0/
0G
0H
0L
0[
0a
0c
0g
0m
0s
0y
0""
0("
