MeuProjeto/mux1x2.vhd
library IEEE;
use IEEE.std_logic_1164.all;
use IEEE.numeric_std.all;

entity mux1x2 is
    port(
        slt: in std_logic;
        in0,in1: in signed(15 downto 0);
        
        out0:out signed(15 downto 0)
    );
end entity mux1x2;

architecture a_mux1x2 of mux1x2 is
    
begin

    out0<= in0 when slt='0' else
            in1 when slt='1' else
            "0000000000000000";

end architecture a_mux1x2;

MeuProjeto/reg16bit.vhd
library IEEE;
use IEEE.std_logic_1164.all;
use IEEE.numeric_std.all;

entity reg16bit is
    port(
        clk :in std_logic;
        rst :in std_logic;
        wr_en: in std_logic;
        data_in: in signed(15 downto 0);
        data_out: out signed(15 downto 0)
    );
end entity reg16bit;

architecture a_reg16bit of reg16bit is
    signal registro: signed(15 downto 0);
begin

   process (clk,rst,wr_en)
   begin
       if rst='1' then
           registro<="0000000000000000";
       elsif wr_en='1' then
           if rising_edge(clk) then
               registro<=data_in;
           end if;
       end if;
   end process;
   
   data_out <= registro;

end architecture a_reg16bit;

MeuProjeto/bancoreg.vhd
library IEEE;
use IEEE.std_logic_1164.all;
use IEEE.numeric_std.all;

entity bancoreg is
    port(
        slt_read1: in unsigned(2 downto 0);
        slt_read2: in unsigned(2 downto 0);
        dados_write: in signed(15 downto 0);
        slt_write: in unsigned(2 downto 0);
        wr_en: in STD_LOGIC;
        clk: in STD_LOGIC;
        rst: in STD_LOGIC;
        
        dados_read1: out signed(15 downto 0);
        dados_read2: out signed(15 downto 0)
    );
end entity bancoreg;

architecture a_bancoreg of bancoreg is
    component reg16bit is
        port
        (
            clk      : IN std_logic ;
            rst      : IN std_logic ;
            wr_en    : IN std_logic ;
            data_in  : IN signed (15 downto 0);
            data_out : OUT signed (15 downto 0)
        );
    end component;
    
    signal wr_en1,wr_en2,wr_en3,wr_en4,wr_en5,wr_en6,wr_en7: STD_LOGIC :='0';
    signal data_out0,data_out1,data_out2,data_out3,data_out4,data_out5,data_out6,data_out7: signed(15 downto 0);
    constant wr_en0:STD_LOGIC:='0';
    
begin

    reg0: reg16bit port map(clk=>clk, rst=>rst, wr_en=>wr_en0, data_in=>dados_write, data_out=>data_out0);
    reg1: reg16bit port map(clk=>clk, rst=>rst, wr_en=>wr_en1, data_in=>dados_write, data_out=>data_out1);
    reg2: reg16bit port map(clk=>clk, rst=>rst, wr_en=>wr_en2, data_in=>dados_write, data_out=>data_out2);
    reg3: reg16bit port map(clk=>clk, rst=>rst, wr_en=>wr_en3, data_in=>dados_write, data_out=>data_out3);
    reg4: reg16bit port map(clk=>clk, rst=>rst, wr_en=>wr_en4, data_in=>dados_write, data_out=>data_out4);
    reg5: reg16bit port map(clk=>clk, rst=>rst, wr_en=>wr_en5, data_in=>dados_write, data_out=>data_out5);
    reg6: reg16bit port map(clk=>clk, rst=>rst, wr_en=>wr_en6, data_in=>dados_write, data_out=>data_out6);
    reg7: reg16bit port map(clk=>clk, rst=>rst, wr_en=>wr_en7, data_in=>dados_write, data_out=>data_out7);
    
    wr_en1<='1' when slt_write = "001" else '0';
    wr_en2<='1' when slt_write = "010" else '0';
    wr_en3<='1' when slt_write = "011" else '0';
    wr_en4<='1' when slt_write = "100" else '0';
    wr_en5<='1' when slt_write = "101" else '0';
    wr_en6<='1' when slt_write = "110" else '0';
    wr_en7<='1' when slt_write = "111" else '0';
    
    dados_read1 <= data_out0 when slt_read1 ="000" else
                    data_out1 when slt_read1 ="001" else
                    data_out2 when slt_read1 ="010" else
                    data_out3 when slt_read1 ="011" else
                    data_out4 when slt_read1 ="100" else
                    data_out5 when slt_read1 ="101" else
                    data_out6 when slt_read1 ="110" else
                    data_out7 when slt_read1 ="111" else
                    "0000000000000000";
    
    dados_read2 <= data_out0 when slt_read2 ="000" else
                    data_out1 when slt_read2 ="001" else
                    data_out2 when slt_read2 ="010" else
                    data_out3 when slt_read2 ="011" else
                    data_out4 when slt_read2 ="100" else
                    data_out5 when slt_read2 ="101" else
                    data_out6 when slt_read2 ="110" else
                    data_out7 when slt_read2 ="111" else
                    "0000000000000000";

end architecture a_bancoreg;

MeuProjeto/ULA.vhd
--Alunos: Jhonny Kristyan Vaz-Tostes de Assis
--        Gabriel Henrique Kwiatkovski Godinho
-- entrega ULA

library ieee;
use ieee.std_logic_1164.all;
use ieee.numeric_std.all;

--------------------
-- 00 = soma
-- 01 = subtração
-- 10 = maior
-- 11 = diferente
--------------------

entity ULA is 
    port(   in_termo_1 : in signed (15 downto 0);
            in_termo_2 : in signed (15 downto 0);

            select_op : in unsigned(1 downto 0);

            out_op_1 : out signed (15 downto 0);
            out_op_2 : out std_logic);
end entity;

architecture a_ULA of ULA is
begin
    out_op_1 <= in_termo_1+in_termo_2 when select_op="00" else
                in_termo_2-in_termo_1 when select_op="01" else
                "0000000000000000";

    out_op_2 <= '1' when select_op="10" and (in_termo_1 > in_termo_2) else
                '1' when select_op="11" and (in_termo_1 /= in_termo_2) else
                '0';

end architecture;

--------------------------------------------------

MeuProjeto/gerenciador.vhd
library IEEE;
use IEEE.std_logic_1164.all;
use IEEE.numeric_std.all;

entity gerenciador is
    port(
        top_level: in signed(15 downto 0);
        clk,rst,wr_en: in STD_LOGIC;
        
        slt_ula: in unsigned(1 downto 0);
        slt_reg_read_1, slt_reg_read_2, slt_reg_write: in unsigned(2 downto 0);
        ALUsrc: in std_logic;
        
        debug_top_level: out signed(15 downto 0)
    );
end entity gerenciador;

architecture a_gerenciador of gerenciador is
    component ULA is
        port
        (
            in_termo_1  : IN signed (15 downto 0);
            in_termo_2  : IN signed (15 downto 0);
            select_op   : IN unsigned(1 downto 0);
            out_op_1    : OUT signed (15 downto 0);
            out_op_2    : OUT std_logic
        );
    end component;
    
    component bancoreg is
        port
        (
            slt_read1   : IN unsigned (2 downto 0);
            slt_read2   : IN unsigned (2 downto 0);
            dados_write : IN signed (15 downto 0);
            slt_write   : IN unsigned (2 downto 0);
            wr_en       : IN STD_LOGIC ;
            clk         : IN STD_LOGIC ;
            rst         : IN STD_LOGIC ;
            dados_read1 : OUT signed (15 downto 0);
            dados_read2 : OUT signed (15 downto 0)
        );
    end component;
    
    component mux1x2 is
        port
        (
            slt  : IN std_logic;
            in0  : IN signed (15 downto 0);
            in1  : IN signed (15 downto 0);
            out0 : OUT signed (15 downto 0)
        );
    end component;
    
    signal out_banco_1,out_banco_2,out_mux,out_ULA: signed(15 downto 0);
    signal out_ULA_2: STD_LOGIC;
    
begin
    ULA1 : ULA port map(
        in_termo_1=>out_banco_1, 
        in_termo_2=>out_mux,
        select_op=>slt_ula, 
        out_op_1=>out_ULA, 
        out_op_2=>out_ULA_2 
    );
    
    banco: bancoreg port map(
        slt_read1=>slt_reg_read_1, 
        slt_read2=>slt_reg_read_2, 
        dados_write=>out_ULA, 
        slt_write=>slt_reg_write, 
        wr_en=>wr_en, 
        clk=>clk, 
        rst=>rst, 
        dados_read1=>out_banco_1, 
        dados_read2=>out_banco_2
    );
    
    mux: mux1x2 port map(
        slt=>ALUsrc, 
        in0=>out_banco_2, 
        in1=>top_level, 
    
        out0=>out_mux
    );
    
    debug_top_level<=out_ULA;


end architecture a_gerenciador;

MeuProjeto/gerenciador_tb.vhd
library IEEE;
use IEEE.std_logic_1164.all;
use IEEE.numeric_std.all;

entity gerenciador_tb is
end entity gerenciador_tb;

architecture a_gerenciador_tb of gerenciador_tb is
    component gerenciador is
        port
        (
            top_level       : IN signed (15 downto 0);
            clk             : IN STD_LOGIC ;
            rst             : IN STD_LOGIC ;
            wr_en           : IN STD_LOGIC ;
            slt_ula         : IN unsigned (1 downto 0);
            slt_reg_read_1  : IN unsigned (2 downto 0);
            slt_reg_read_2  : IN unsigned (2 downto 0);
            slt_reg_write   : IN unsigned (2 downto 0);
            ALUsrc          : IN std_logic; 
            debug_top_level : OUT signed (15 downto 0)
        );
    end component;


    constant period_time : time := 100 ns;
    signal finished : std_logic := '0';
    signal clk, reset : std_logic;

    signal top_level, debug_top_level :signed (15 downto 0):="0000000000000000";
    signal wr_en, ALUsrc: std_logic:='0';
    signal slt_ula : unsigned (1 downto 0):="00";
    signal slt_reg_read_1, slt_reg_read_2, slt_reg_write :  unsigned (2 downto 0):="000";



begin

    uut: gerenciador port map(  top_level=>top_level,
                                clk=>clk,
                                rst=>reset,
                                wr_en=>wr_en,
                                slt_ula=>slt_ula,
                                slt_reg_read_1=>slt_reg_read_1,
                                slt_reg_read_2=>slt_reg_read_2,
                                slt_reg_write=>slt_reg_write,
                                ALUsrc=>ALUsrc,
                                debug_top_level=>debug_top_level);

--TESTES

    reset_global: process
    begin
        reset <= '1';
        wait for period_time*2; -- espera 2 clocks, pra garantir
        reset <= '0';
        wait;
    end process;
  
    sim_time_proc: process
    begin
        wait for 1000 ns;
        finished <= '1';
        wait;
    end process sim_time_proc;

    clk_proc: process
    begin -- gera clock até que sim_time_proc termine
        while finished /= '1' loop
        clk <= '0';
        wait for period_time/2;
        clk <= '1';
        wait for period_time/2;
        end loop;
        wait;
    end process clk_proc;  
    
    process 
    begin
        --addi $1,$0,3
        wait for 200 ns;
        top_level <= "0000000000000011";
        slt_reg_write <= "001";
        wr_en <= '1';
        ALUsrc <= '1';
        slt_reg_read_1 <= "000";
        slt_ula <= "00";
      
        --addi $4,$0,4
        wait for 100 ns;
        top_level <= "0000000000000100";
        slt_reg_write <= "100";
       
        --add $5,$1,$4
        wait for 100 ns;
        ALUsrc <= '0';
        slt_reg_read_1 <= "001";
        slt_reg_read_2 <= "100";
        slt_reg_write <= "101";
       
        --addi $6,$0,2
        wait for 100 ns;
        ALUsrc <= '1';
        top_level <= "0000000000000010";
        slt_reg_write <= "110";
        slt_reg_read_1 <= "000";

        --sub $1,$5,$6
        wait for 100 ns;
        slt_ula <= "01";
        ALUsrc <= '0';
        slt_reg_read_1 <= "110";
        slt_reg_read_2 <= "101";
        slt_reg_write <= "001";
        wait for 100 ns;


        wr_en <= '0';
        wait;
    end process;
end architecture a_gerenciador_tb;

MeuProjeto/gerenciador_tb.vcd
$date
  Thu Nov 04 22:03:10 2021
$end
$version
  GHDL v0
$end
$timescale
  1 fs
$end
$scope module standard $end
$upscope $end
$scope module std_logic_1164 $end
$upscope $end
$scope module numeric_std $end
$upscope $end
$scope module gerenciador_tb $end
$var reg 1 ! finished $end
$var reg 1 " clk $end
$var reg 1 # reset $end
$var reg 16 $ top_level[15:0] $end
$var reg 16 % debug_top_level[15:0] $end
$var reg 1 & wr_en $end
$var reg 1 ' alusrc $end
$var reg 2 ( slt_ula[1:0] $end
$var reg 3 ) slt_reg_read_1[2:0] $end
$var reg 3 * slt_reg_read_2[2:0] $end
$var reg 3 + slt_reg_write[2:0] $end
$scope module uut $end
$var reg 16 , top_level[15:0] $end
$var reg 1 - clk $end
$var reg 1 . rst $end
$var reg 1 / wr_en $end
$var reg 2 0 slt_ula[1:0] $end
$var reg 3 1 slt_reg_read_1[2:0] $end
$var reg 3 2 slt_reg_read_2[2:0] $end
$var reg 3 3 slt_reg_write[2:0] $end
$var reg 1 4 alusrc $end
$var reg 16 5 debug_top_level[15:0] $end
$var reg 16 6 out_banco_1[15:0] $end
$var reg 16 7 out_banco_2[15:0] $end
$var reg 16 8 out_mux[15:0] $end
$var reg 16 9 out_ula[15:0] $end
$var reg 1 : out_ula_2 $end
$scope module ula1 $end
$var reg 16 ; in_termo_1[15:0] $end
$var reg 16 < in_termo_2[15:0] $end
$var reg 2 = select_op[1:0] $end
$var reg 16 > out_op_1[15:0] $end
$var reg 1 ? out_op_2 $end
$upscope $end
$scope module banco $end
$var reg 3 @ slt_read1[2:0] $end
$var reg 3 A slt_read2[2:0] $end
$var reg 16 B dados_write[15:0] $end
$var reg 3 C slt_write[2:0] $end
$var reg 1 D wr_en $end
$var reg 1 E clk $end
$var reg 1 F rst $end
$var reg 16 G dados_read1[15:0] $end
$var reg 16 H dados_read2[15:0] $end
$var reg 1 I wr_en1 $end
$var reg 1 J wr_en2 $end
$var reg 1 K wr_en3 $end
$var reg 1 L wr_en4 $end
$var reg 1 M wr_en5 $end
$var reg 1 N wr_en6 $end
$var reg 1 O wr_en7 $end
$var reg 16 P data_out0[15:0] $end
$var reg 16 Q data_out1[15:0] $end
$var reg 16 R data_out2[15:0] $end
$var reg 16 S data_out3[15:0] $end
$var reg 16 T data_out4[15:0] $end
$var reg 16 U data_out5[15:0] $end
$var reg 16 V data_out6[15:0] $end
$var reg 16 W data_out7[15:0] $end
$scope module reg0 $end
$var reg 1 X clk $end
$var reg 1 Y rst $end
$var reg 1 Z wr_en $end
$var reg 16 [ data_in[15:0] $end
$var reg 16 \ data_out[15:0] $end
$var reg 16 ] registro[15:0] $end
$upscope $end
$scope module reg1 $end
$var reg 1 ^ clk $end
$var reg 1 _ rst $end
$var reg 1 ` wr_en $end
$var reg 16 a data_in[15:0] $end
$var reg 16 b data_out[15:0] $end
$var reg 16 c registro[15:0] $end
$upscope $end
$scope module reg2 $end
$var reg 1 d clk $end
$var reg 1 e rst $end
$var reg 1 f wr_en $end
$var reg 16 g data_in[15:0] $end
$var reg 16 h data_out[15:0] $end
$var reg 16 i registro[15:0] $end
$upscope $end
$scope module reg3 $end
$var reg 1 j clk $end
$var reg 1 k rst $end
$var reg 1 l wr_en $end
$var reg 16 m data_in[15:0] $end
$var reg 16 n data_out[15:0] $end
$var reg 16 o registro[15:0] $end
$upscope $end
$scope module reg4 $end
$var reg 1 p clk $end
$var reg 1 q rst $end
$var reg 1 r wr_en $end
$var reg 16 s data_in[15:0] $end
$var reg 16 t data_out[15:0] $end
$var reg 16 u registro[15:0] $end
$upscope $end
$scope module reg5 $end
$var reg 1 v clk $end
$var reg 1 w rst $end
$var reg 1 x wr_en $end
$var reg 16 y data_in[15:0] $end
$var reg 16 z data_out[15:0] $end
$var reg 16 { registro[15:0] $end
$upscope $end
$scope module reg6 $end
$var reg 1 | clk $end
$var reg 1 } rst $end
$var reg 1 !" wr_en $end
$var reg 16 "" data_in[15:0] $end
$var reg 16 #" data_out[15:0] $end
$var reg 16 $" registro[15:0] $end
$upscope $end
$scope module reg7 $end
$var reg 1 %" clk $end
$var reg 1 &" rst $end
$var reg 1 '" wr_en $end
$var reg 16 (" data_in[15:0] $end
$var reg 16 )" data_out[15:0] $end
$var reg 16 *" registro[15:0] $end
$upscope $end
$upscope $end
$scope module mux $end
$var reg 1 +" slt $end
$var reg 16 ," in0[15:0] $end
$var reg 16 -" in1[15:0] $end
$var reg 16 ." out0[15:0] $end
$upscope $end
$upscope $end
$upscope $end
$enddefinitions $end
#0
0!
0"
1#
b0000000000000000 $
b0000000000000000 %
0&
0'
b00 (
b000 )
b000 *
b000 +
b0000000000000000 ,
0-
1.
0/
b00 0
b000 1
b000 2
b000 3
04
b0000000000000000 5
b0000000000000000 6
b0000000000000000 7
b0000000000000000 8
b0000000000000000 9
0:
b0000000000000000 ;
b0000000000000000 <
b00 =
b0000000000000000 >
0?
b000 @
b000 A
b0000000000000000 B
b000 C
0D
0E
1F
b0000000000000000 G
b0000000000000000 H
0I
0J
0K
0L
0M
0N
0O
b0000000000000000 P
b0000000000000000 Q
b0000000000000000 R
b0000000000000000 S
b0000000000000000 T
b0000000000000000 U
b0000000000000000 V
b0000000000000000 W
0X
1Y
0Z
b0000000000000000 [
b0000000000000000 \
b0000000000000000 ]
0^
1_
0`
b0000000000000000 a
b0000000000000000 b
b0000000000000000 c
0d
1e
0f
b0000000000000000 g
b0000000000000000 h
b0000000000000000 i
0j
1k
0l
b0000000000000000 m
b0000000000000000 n
b0000000000000000 o
0p
1q
0r
b0000000000000000 s
b0000000000000000 t
b0000000000000000 u
0v
1w
0x
b0000000000000000 y
b0000000000000000 z
b0000000000000000 {
0|
1}
0!"
b0000000000000000 ""
b0000000000000000 #"
b0000000000000000 $"
0%"
1&"
0'"
b0000000000000000 ("
b0000000000000000 )"
b0000000000000000 *"
0+"
b0000000000000000 ,"
b0000000000000000 -"
b0000000000000000 ."
#50000000
1"
1-
1E
1X
1^
1d
1j
1p
1v
1|
1%"
#100000000
0"
0-
0E
0X
0^
0d
0j
0p
0v
0|
0%"
#150000000
1"
1-
1E
1X
1^
1d
1j
1p
1v
1|
1%"
#200000000
0"
0#
b0000000000000011 $
b0000000000000011 %
1&
1'
b001 +
b0000000000000011 ,
0-
0.
1/
b001 3
14
b0000000000000011 5
b0000000000000011 8
b0000000000000011 9
b0000000000000011 <
b0000000000000011 >
b0000000000000011 B
b001 C
1D
0E
0F
1I
0X
0Y
b0000000000000011 [
0^
0_
1`
b0000000000000011 a
0d
0e
b0000000000000011 g
0j
0k
b0000000000000011 m
0p
0q
b0000000000000011 s
0v
0w
b0000000000000011 y
0|
0}
b0000000000000011 ""
0%"
0&"
b0000000000000011 ("
1+"
b0000000000000011 -"
b0000000000000011 ."
#250000000
1"
1-
1E
b0000000000000011 Q
1X
1^
b0000000000000011 b
b0000000000000011 c
1d
1j
1p
1v
1|
1%"
#300000000
0"
b0000000000000100 $
b0000000000000100 %
b100 +
b0000000000000100 ,
0-
b100 3
b0000000000000100 5
b0000000000000100 8
b0000000000000100 9
b0000000000000100 <
b0000000000000100 >
b0000000000000100 B
b100 C
0E
0I
1L
0X
b0000000000000100 [
0^
0`
b0000000000000100 a
0d
b0000000000000100 g
0j
b0000000000000100 m
0p
1r
b0000000000000100 s
0v
b0000000000000100 y
0|
b0000000000000100 ""
0%"
b0000000000000100 ("
b0000000000000100 -"
b0000000000000100 ."
#350000000
1"
1-
1E
b0000000000000100 T
1X
1^
1d
1j
1p
b0000000000000100 t
b0000000000000100 u
1v
1|
1%"
#400000000
0"
b0000000000000111 %
0'
b001 )
b100 *
b101 +
0-
b001 1
b100 2
b101 3
04
b0000000000000111 5
b0000000000000011 6
b0000000000000100 7
b0000000000000100 8
b0000000000000111 9
b0000000000000011 ;
b0000000000000100 <
b0000000000000111 >
b001 @
b100 A
b0000000000000111 B
b101 C
0E
b0000000000000011 G
b0000000000000100 H
0L
1M
0X
b0000000000000111 [
0^
b0000000000000111 a
0d
b0000000000000111 g
0j
b0000000000000111 m
0p
0r
b0000000000000111 s
0v
1x
b0000000000000111 y
0|
b0000000000000111 ""
0%"
b0000000000000111 ("
0+"
b0000000000000100 ,"
b0000000000000100 ."
#450000000
1"
1-
1E
b0000000000000111 U
1X
1^
1d
1j
1p
1v
b0000000000000111 z
b0000000000000111 {
1|
1%"
#500000000
0"
b0000000000000010 $
b0000000000000010 %
1'
b000 )
b110 +
b0000000000000010 ,
0-
b000 1
b110 3
14
b0000000000000010 5
b0000000000000000 6
b0000000000000010 8
b0000000000000010 9
b0000000000000000 ;
b0000000000000010 <
b0000000000000010 >
b000 @
b0000000000000010 B
b110 C
0E
b0000000000000000 G
0M
1N
0X
b0000000000000010 [
0^
b0000000000000010 a
0d
b0000000000000010 g
0j
b0000000000000010 m
0p
b0000000000000010 s
0v
0x
b0000000000000010 y
0|
1!"
b0000000000000010 ""
0%"
b0000000000000010 ("
1+"
b0000000000000010 -"
b0000000000000010 ."
#550000000
1"
1-
1E
b0000000000000010 V
1X
1^
1d
1j
1p
1v
1|
b0000000000000010 #"
b0000000000000010 $"
1%"
#600000000
0"
b1111111111111011 %
0'
b01 (
b110 )
b101 *
b001 +
0-
b01 0
b110 1
b101 2
b001 3
04
b1111111111111011 5
b0000000000000010 6
b0000000000000111 7
b0000000000000111 8
b1111111111111011 9
b0000000000000010 ;
b0000000000000111 <
b01 =
b1111111111111011 >
b110 @
b101 A
b1111111111111011 B
b001 C
0E
b0000000000000010 G
b0000000000000111 H
1I
0N
0X
b1111111111111011 [
0^
1`
b1111111111111011 a
0d
b1111111111111011 g
0j
b1111111111111011 m
0p
b1111111111111011 s
0v
b1111111111111011 y
0|
0!"
b1111111111111011 ""
0%"
b1111111111111011 ("
0+"
b0000000000000111 ,"
b0000000000000111 ."
#650000000
1"
1-
1E
b1111111111111011 Q
1X
1^
b1111111111111011 b
b1111111111111011 c
1d
1j
1p
1v
1|
1%"
#700000000
0"
0&
0-
0/
0D
0E
0I
0X
0^
0`
0d
0j
0p
0v
0|
0%"
#750000000
1"
1-
1E
1X
1^
1d
1j
1p
1v
1|
1%"
#800000000
0"
0-
0E
0X
0^
0d
0j
0p
0v
0|
0%"
#850000000
1"
1-
1E
1X
1^
1d
1j
1p
1v
1|
1%"
#900000000
0"
0-
0E
0X
0^
0d
0j
0p
0v
0|
0%"
#950000000
1"
1-
1E
1X
1^
1d
1j
1p
1v
1|
1%"
#1000000000
1!
0"
0-
0E
0X
0^
0d
0j
0p
0v
0|
0%"
