MeuProjeto/maquina_de_estados.vhd
library ieee;
use ieee.std_logic_1164.all;
use ieee.numeric_std.all;

entity maquina_de_estados is
    port(
        clk: in std_logic;
        reset: in std_logic;
        estado: out std_logic
    );
end entity maquina_de_estados;

architecture a_maquina_de_estados of maquina_de_estados is 
    signal estado_s: std_logic;

    begin
    process (clk, reset)
    begin
        if reset = '1' then estado_s<='0';
        elsif rising_edge(clk) then
            estado_s <= not estado_s;
        end if;
    end process;
    estado <= estado_s;

end architecture a_maquina_de_estados;

MeuProjeto/maquina_de_estados_tb.vhd
library ieee;
use ieee.std_logic_1164.all;
use ieee.numeric_std.all;

entity maquina_de_estados_tb is
end entity;

architecture a_maquina_de_estados_tb of maquina_de_estados_tb is
    component maquina_de_estados
        port(
            clk: in std_logic;
            reset: in std_logic;
            estado: out std_logic
        );
    end component;

    constant period_time : time := 50 ns;
    signal finished : std_logic := '0';
    signal clk, reset : std_logic;
    signal estado : std_logic;


    begin
        uut: maquina_de_estados port map(   clk=>clk,
                                            estado=>estado,
                                            reset=>reset
                                        );


    reset_global: process
    begin
        reset <= '1';
        wait for period_time*2; -- espera 2 clocks, pra garantir
        reset <= '0';
        wait;
    end process;
  
    sim_time_proc: process
    begin
        wait for 400 ns;
        finished <= '1';
        wait;
    end process sim_time_proc;

    clk_proc: process
    begin -- gera clock até que sim_time_proc termine
        while finished /= '1' loop
        clk <= '0';
        wait for period_time/2;
        clk <= '1';
        wait for period_time/2;
        end loop;
        wait;
    end process clk_proc;  

    process 
    begin
         
        wait;
    end process;
end architecture a_maquina_de_estados_tb;

MeuProjeto/maquina_de_estados_tb.vcd
$date
  Thu Nov 11 17:02:19 2021
$end
$version
  GHDL v0
$end
$timescale
  1 fs
$end
$scope module standard $end
$upscope $end
$scope module std_logic_1164 $end
$upscope $end
$scope module numeric_std $end
$upscope $end
$scope module maquina_de_estados_tb $end
$var reg 1 ! finished $end
$var reg 1 " clk $end
$var reg 1 # reset $end
$var reg 1 $ estado $end
$scope module uut $end
$var reg 1 % clk $end
$var reg 1 & reset $end
$var reg 1 ' estado $end
$var reg 1 ( estado_s $end
$upscope $end
$upscope $end
$enddefinitions $end
#0
0!
0"
1#
0$
0%
1&
0'
0(
#25000000
1"
1%
#50000000
0"
0%
#75000000
1"
1%
#100000000
0"
0#
0%
0&
#125000000
1"
1$
1%
1'
1(
#150000000
0"
0%
#175000000
1"
0$
1%
0'
0(
#200000000
0"
0%
#225000000
1"
1$
1%
1'
1(
#250000000
0"
0%
#275000000
1"
0$
1%
0'
0(
#300000000
0"
0%
#325000000
1"
1$
1%
1'
1(
#350000000
0"
0%
#375000000
1"
0$
1%
0'
0(
#400000000
1!
0"
0%
#425000000
1"
1$
1%
1'
1(
