MeuProjeto/maquina_de_estados.vhd
library ieee;
use ieee.std_logic_1164.all;
use ieee.numeric_std.all;

entity maquina_de_estados is
    port(
        clk: in std_logic;
        reset: in std_logic;
        estado: out std_logic
    );
end entity maquina_de_estados;

architecture a_maquina_de_estados of maquina_de_estados is 
    signal estado_s: std_logic;

    begin
    process (clk, reset)
    begin
        if reset = '1' then estado_s<='0';
        elsif rising_edge(clk) then
            estado_s <= not estado_s;
        end if;
    end process;
    estado <= estado_s;

end architecture a_maquina_de_estados;

MeuProjeto/ROM.vhd
library ieee;
use ieee.std_logic_1164.all;
use ieee.numeric_std.all;

entity rom is
    port( clk : in std_logic;
        endereco : in unsigned(6 downto 0);--memória de programa = 4Kbytes 4000bytes = 32000 bits
        dado : out signed(16 downto 0)    --32000/17=1882 endereços de 17 bits
    );
end entity;

architecture a_rom of rom is
    type mem is array (0 to 127) of signed(16 downto 0);--trocar futuramente 127 por 1881
    constant conteudo_rom : mem := (
        -- caso endereco => conteudo
        0 => "00000000000001000",
        1 => "00000000000000111",
        2 => "00000000000000100",
        -- abaixo: casos omissos => (zero em todos os bits)
        others => (others=>'0')
    );

begin
   process(clk)
   begin
      if(rising_edge(clk)) then
         dado <= conteudo_rom(to_integer(endereco));
      end if;
   end process;
end architecture;

MeuProjeto/reg7bit.vhd
library IEEE;
use IEEE.std_logic_1164.all;
use IEEE.numeric_std.all;

entity reg7bit is
    port(
        clk :in std_logic;
        rst :in std_logic;
        wr_en: in std_logic;
        data_in: in unsigned(6 downto 0);
        data_out: out unsigned(6 downto 0)
    );
end entity reg7bit;

architecture a_reg7bit of reg7bit is
    signal registro: unsigned(6 downto 0);
begin

   process (clk,rst,wr_en)
   begin
       if rst='1' then
           registro<="0000000";
       elsif wr_en='1' then
           if rising_edge(clk) then
               registro<=data_in;
           end if;
       end if;
   end process;
   
   data_out <= registro;

end architecture a_reg7bit;

MeuProjeto/PC_control.vhd
library ieee;
use ieee.std_logic_1164.all;
use ieee.numeric_std.all;

entity PC_control is 
    port(
        clk :in std_logic;
        rst :in std_logic;
        wr_en: in std_logic;
        data_in: in unsigned(6 downto 0);
        data_out: out unsigned(6 downto 0);
        top_lvl: out signed(16 downto 0)
    );    
end entity PC_control;

architecture a_PC_control of PC_control is
    component reg7bit is
        port(
            clk :in std_logic;
            rst :in std_logic;
            wr_en: in std_logic;
            data_in: in unsigned(6 downto 0);
            data_out: out unsigned(6 downto 0)
        );
    end component;

    component ROM is
        port( clk : in std_logic;
            endereco : in unsigned(6 downto 0);--memória de programa = 4Kbytes 4000bytes = 32000 bits
            dado : out signed(16 downto 0)    --32000/17=1882 endereços de 17 bits
            );
    end component;

    component maquina_de_estados is
        port(
            clk: in std_logic;
            reset: in std_logic;
            estado: out std_logic
        );
    end component;

    signal resultado: unsigned(6 downto 0):="0000000";
    signal endereco : unsigned(6 downto 0);
    signal dado : signed(16 downto 0);
    signal estado_maq: std_logic;

begin
    PC1: reg7bit port map( clk=>clk,
                            rst=>rst,
                            wr_en=>wr_en,
                            data_in=>resultado,
                            data_out=>data_out
                        );
    
    ROM1: ROM port map(  clk=>clk,
                        endereco=>resultado,
                        dado=>dado
                    );

    ME1: maquina_de_estados port map(    clk=>clk,
                                        reset=>rst,
                                        estado=>estado_maq
                                    );

    
    
    resultado <=    resultado+1 when wr_en = '1' and rising_edge(clk) and estado_maq='1' else
                    resultado;
    top_lvl <= dado when estado_maq='0' else
                "00000000000000000";
    
end architecture a_PC_control;

MeuProjeto/PC_control_tb.vhd
library ieee;
use ieee.std_logic_1164.all;
use ieee.numeric_std.all;

entity PC_control_tb is    
end entity PC_control_tb;

architecture a_PC_control_tb of PC_control_tb is
    component PC_control
        port(
            clk :in std_logic;
            rst :in std_logic;
            wr_en: in std_logic;
            data_in: in unsigned(6 downto 0);
            data_out: out unsigned(6 downto 0);
            top_lvl: out signed(16 downto 0)
        );
    end component;

    signal wr_en: std_logic;
    signal data_in, data_out: unsigned(6 downto 0);

    constant period_time : time := 50 ns;
    signal finished : std_logic := '0';
    signal clk, reset : std_logic;
    signal top_lvl: signed(16 downto 0);

begin
    uut: PC_control port map(   clk=>clk,
                                rst=>reset,
                                wr_en=>wr_en,
                                data_in=>data_in,
                                data_out=>data_out,
                                top_lvl=>top_lvl
                            );

    reset_global: process
    begin
        reset <= '1';
        wait for period_time*2; -- espera 2 clocks, pra garantir
        reset <= '0';
        wait;
    end process;
  
    sim_time_proc: process
    begin
        wait for 400 ns;
        finished <= '1';
        wait;
    end process sim_time_proc;

    clk_proc: process
    begin -- gera clock até que sim_time_proc termine
        while finished /= '1' loop
        clk <= '0';
        wait for period_time/2;
        clk <= '1';
        wait for period_time/2;
        end loop;
        wait;
    end process clk_proc;  

    process 
    begin
        wait for 100 ns;
        wr_en <='1';
        data_in <="0000000";
        wait for 50 ns;
        wait for 50 ns;
        wait;
    end process;

end architecture a_PC_control_tb;

MeuProjeto/PC_control_tb.vcd
$date
  Thu Nov 11 20:34:06 2021
$end
$version
  GHDL v0
$end
$timescale
  1 fs
$end
$scope module standard $end
$upscope $end
$scope module std_logic_1164 $end
$upscope $end
$scope module numeric_std $end
$upscope $end
$scope module pc_control_tb $end
$var reg 1 ! wr_en $end
$var reg 7 " data_in[6:0] $end
$var reg 7 # data_out[6:0] $end
$var reg 1 $ finished $end
$var reg 1 % clk $end
$var reg 1 & reset $end
$var reg 17 ' top_lvl[16:0] $end
$scope module uut $end
$var reg 1 ( clk $end
$var reg 1 ) rst $end
$var reg 1 * wr_en $end
$var reg 7 + data_in[6:0] $end
$var reg 7 , data_out[6:0] $end
$var reg 17 - top_lvl[16:0] $end
$var reg 7 . resultado[6:0] $end
$var reg 7 / endereco[6:0] $end
$var reg 17 0 dado[16:0] $end
$var reg 1 1 estado_maq $end
$scope module pc1 $end
$var reg 1 2 clk $end
$var reg 1 3 rst $end
$var reg 1 4 wr_en $end
$var reg 7 5 data_in[6:0] $end
$var reg 7 6 data_out[6:0] $end
$var reg 7 7 registro[6:0] $end
$upscope $end
$scope module rom1 $end
$var reg 1 8 clk $end
$var reg 7 9 endereco[6:0] $end
$var reg 17 : dado[16:0] $end
$upscope $end
$scope module me1 $end
$var reg 1 ; clk $end
$var reg 1 < reset $end
$var reg 1 = estado $end
$var reg 1 > estado_s $end
$upscope $end
$upscope $end
$upscope $end
$enddefinitions $end
#0
U!
bUUUUUUU "
b0000000 #
0$
0%
1&
bUUUUUUUUUUUUUUUUU '
0(
1)
U*
bUUUUUUU +
b0000000 ,
bUUUUUUUUUUUUUUUUU -
b0000000 .
bUUUUUUU /
bUUUUUUUUUUUUUUUUU 0
01
02
13
U4
b0000000 5
b0000000 6
b0000000 7
08
b0000000 9
bUUUUUUUUUUUUUUUUU :
0;
1<
0=
0>
#25000000
1%
b00000000000001000 '
1(
b00000000000001000 -
b00000000000001000 0
12
18
b00000000000001000 :
1;
#50000000
0%
0(
02
08
0;
#75000000
1%
1(
12
18
1;
#100000000
1!
b0000000 "
0%
0&
0(
0)
1*
b0000000 +
02
03
14
08
0;
0<
#125000000
1%
b00000000000000000 '
1(
b00000000000000000 -
11
12
18
1;
1=
1>
#150000000
0%
0(
02
08
0;
#175000000
1%
b00000000000001000 '
1(
b00000000000001000 -
b0000001 .
01
12
b0000001 5
18
b0000001 9
1;
0=
0>
#200000000
0%
0(
02
08
0;
#225000000
b0000001 #
1%
b00000000000000000 '
1(
b0000001 ,
b00000000000000000 -
b00000000000000111 0
11
12
b0000001 6
b0000001 7
18
b00000000000000111 :
1;
1=
1>
#250000000
0%
0(
02
08
0;
#275000000
1%
b00000000000000111 '
1(
b00000000000000111 -
b0000010 .
01
12
b0000010 5
18
b0000010 9
1;
0=
0>
#300000000
0%
0(
02
08
0;
#325000000
b0000010 #
1%
b00000000000000000 '
1(
b0000010 ,
b00000000000000000 -
b00000000000000100 0
11
12
b0000010 6
b0000010 7
18
b00000000000000100 :
1;
1=
1>
#350000000
0%
0(
02
08
0;
#375000000
1%
b00000000000000100 '
1(
b00000000000000100 -
b0000011 .
01
12
b0000011 5
18
b0000011 9
1;
0=
0>
#400000000
1$
0%
0(
02
08
0;
#425000000
b0000011 #
1%
b00000000000000000 '
1(
b0000011 ,
b00000000000000000 -
b00000000000000000 0
11
12
b0000011 6
b0000011 7
18
b00000000000000000 :
1;
1=
1>
