MeuProjeto/reg16bit.vhd
library IEEE;
use IEEE.std_logic_1164.all;
use IEEE.numeric_std.all;

entity reg16bit is
    port(
        clk :in std_logic;
        rst :in std_logic;
        wr_en: in std_logic;
        data_in: in signed(15 downto 0);
        data_out: out signed(15 downto 0)
    );
end entity reg16bit;

architecture a_reg16bit of reg16bit is
    signal registro: signed(15 downto 0);
begin

   process (clk,rst,wr_en)
   begin
       if rst='1' then
           registro<="0000000000000000";
       elsif wr_en='1' then
           if rising_edge(clk) then
               registro<=data_in;
           end if;
       end if;
   end process;
   
   data_out <= registro;

end architecture a_reg16bit;

MeuProjeto/PC_control.vhd
library ieee;
use ieee.std_logic_1164.all;
use ieee.numeric_std.all;

entity PC_control is 
    port(
        clk :in std_logic;
        rst :in std_logic;
        wr_en: in std_logic;
        data_in: in signed(15 downto 0);
        data_out: out signed(15 downto 0);
        incrementa: in std_logic

    );    
end entity PC_control;

architecture a_PC_control of PC_control is
    component reg16bit
        port(
            clk :in std_logic;
            rst :in std_logic;
            wr_en: in std_logic;
            data_in: in signed(15 downto 0);
            data_out: out signed(15 downto 0)
        );
    end component;

    signal resultado: signed(15 downto 0);
begin
    PC: reg16bit port map( clk=>clk,
                            rst=>rst,
                            wr_en=>wr_en,
                            data_in=>resultado,
                            data_out=>data_out
                        );

    
    resultado <=   data_in+1 when incrementa = '1' else
                   data_in;
    
end architecture a_PC_control;

MeuProjeto/PC_control_tb.vhd
library ieee;
use ieee.std_logic_1164.all;
use ieee.numeric_std.all;

entity PC_control_tb is    
end entity PC_control_tb;

architecture a_PC_control_tb of PC_control_tb is
    component PC_control
        port(
            clk :in std_logic;
            rst :in std_logic;
            wr_en: in std_logic;
            data_in: in signed(15 downto 0);
            data_out: out signed(15 downto 0);
            incrementa: in std_logic
        );
    end component;

    signal wr_en: std_logic;
    signal incrementa: std_logic :='0';
    signal data_in, data_out: signed(15 downto 0);

    constant period_time : time := 50 ns;
    signal finished : std_logic := '0';
    signal clk, reset : std_logic;

begin
    uut: PC_control port map(   clk=>clk,
                                rst=>reset,
                                wr_en=>wr_en,
                                data_in=>data_in,
                                data_out=>data_out,
                                incrementa=>incrementa
                            );

    reset_global: process
    begin
        reset <= '1';
        wait for period_time*2; -- espera 2 clocks, pra garantir
        reset <= '0';
        wait;
    end process;
  
    sim_time_proc: process
    begin
        wait for 400 ns;
        finished <= '1';
        wait;
    end process sim_time_proc;

    clk_proc: process
    begin -- gera clock até que sim_time_proc termine
        while finished /= '1' loop
        clk <= '0';
        wait for period_time/2;
        clk <= '1';
        wait for period_time/2;
        end loop;
        wait;
    end process clk_proc;  

    process 
    begin
        wr_en <='1';
        incrementa<='1';
        data_in <="0000000000000000";
        wait for 50 ns;
        incrementa<='0';
        incrementa<='1';
        wait for 50 ns;
        wait;
    end process;

end architecture a_PC_control_tb;

MeuProjeto/PC_control_tb.vcd
$date
  Thu Nov 11 19:12:17 2021
$end
$version
  GHDL v0
$end
$timescale
  1 fs
$end
$scope module standard $end
$upscope $end
$scope module std_logic_1164 $end
$upscope $end
$scope module numeric_std $end
$upscope $end
$scope module pc_control_tb $end
$var reg 1 ! wr_en $end
$var reg 1 " incrementa $end
$var reg 16 # data_in[15:0] $end
$var reg 16 $ data_out[15:0] $end
$var reg 1 % finished $end
$var reg 1 & clk $end
$var reg 1 ' reset $end
$scope module uut $end
$var reg 1 ( clk $end
$var reg 1 ) rst $end
$var reg 1 * wr_en $end
$var reg 16 + data_in[15:0] $end
$var reg 16 , data_out[15:0] $end
$var reg 1 - incrementa $end
$var reg 16 . resultado[15:0] $end
$scope module pc $end
$var reg 1 / clk $end
$var reg 1 0 rst $end
$var reg 1 1 wr_en $end
$var reg 16 2 data_in[15:0] $end
$var reg 16 3 data_out[15:0] $end
$var reg 16 4 registro[15:0] $end
$upscope $end
$upscope $end
$upscope $end
$enddefinitions $end
#0
1!
1"
b0000000000000000 #
b0000000000000000 $
0%
0&
1'
0(
1)
1*
b0000000000000000 +
b0000000000000000 ,
1-
b0000000000000000 .
0/
10
11
b0000000000000000 2
b0000000000000000 3
b0000000000000000 4
#25000000
1&
1(
b0000000000000001 .
1/
b0000000000000001 2
#50000000
0&
0(
0/
#75000000
1&
1(
b0000000000000010 .
1/
b0000000000000010 2
#100000000
0&
0'
0(
0)
0/
00
#125000000
b0000000000000010 $
1&
1(
b0000000000000010 ,
b0000000000000011 .
1/
b0000000000000011 2
b0000000000000010 3
b0000000000000010 4
#150000000
0&
0(
0/
#175000000
b0000000000000011 $
1&
1(
b0000000000000011 ,
b0000000000000100 .
1/
b0000000000000100 2
b0000000000000011 3
b0000000000000011 4
#200000000
0&
0(
0/
#225000000
b0000000000000100 $
1&
1(
b0000000000000100 ,
b0000000000000101 .
1/
b0000000000000101 2
b0000000000000100 3
b0000000000000100 4
#250000000
0&
0(
0/
#275000000
b0000000000000101 $
1&
1(
b0000000000000101 ,
b0000000000000110 .
1/
b0000000000000110 2
b0000000000000101 3
b0000000000000101 4
#300000000
0&
0(
0/
#325000000
b0000000000000110 $
1&
1(
b0000000000000110 ,
b0000000000000111 .
1/
b0000000000000111 2
b0000000000000110 3
b0000000000000110 4
#350000000
0&
0(
0/
#375000000
b0000000000000111 $
1&
1(
b0000000000000111 ,
b0000000000001000 .
1/
b0000000000001000 2
b0000000000000111 3
b0000000000000111 4
#400000000
1%
0&
0(
0/
#425000000
b0000000000001000 $
1&
1(
b0000000000001000 ,
b0000000000001001 .
1/
b0000000000001001 2
b0000000000001000 3
b0000000000001000 4
