MeuProjeto/mux1x2.vhd
library IEEE;
use IEEE.std_logic_1164.all;
use IEEE.numeric_std.all;

entity mux1x2 is
    port(
        slt: in std_logic;
        in0,in1: in signed(15 downto 0);
        
        out0:out signed(15 downto 0)
    );
end entity mux1x2;

architecture a_mux1x2 of mux1x2 is
    
begin

    out0<= in0 when slt='0' else
            in1 when slt='1' else
            "0000000000000000";

end architecture a_mux1x2;

MeuProjeto/reg16bit.vhd
library IEEE;
use IEEE.std_logic_1164.all;
use IEEE.numeric_std.all;

entity reg16bit is
    port(
        clk :in std_logic;
        rst :in std_logic;
        wr_en: in std_logic;
        data_in: in signed(15 downto 0);
        data_out: out signed(15 downto 0)
    );
end entity reg16bit;

architecture a_reg16bit of reg16bit is
    signal registro: signed(15 downto 0);
begin

   process (clk,rst,wr_en)
   begin
       if rst='1' then
           registro<="0000000000000000";
       elsif wr_en='1' then
           if rising_edge(clk) then
               registro<=data_in;
           end if;
       end if;
   end process;
   
   data_out <= registro;

end architecture a_reg16bit;

MeuProjeto/bancoreg.vhd
library IEEE;
use IEEE.std_logic_1164.all;
use IEEE.numeric_std.all;

entity bancoreg is
    port(
        slt_read1: in unsigned(2 downto 0);
        slt_read2: in unsigned(2 downto 0);
        dados_write: in signed(15 downto 0);
        slt_write: in unsigned(2 downto 0);
        wr_en: in STD_LOGIC;
        clk: in STD_LOGIC;
        rst: in STD_LOGIC;
        
        dados_read1: out signed(15 downto 0);
        dados_read2: out signed(15 downto 0)
    );
end entity bancoreg;

architecture a_bancoreg of bancoreg is
    component reg16bit is
        port
        (
            clk      : IN std_logic ;
            rst      : IN std_logic ;
            wr_en    : IN std_logic ;
            data_in  : IN signed (15 downto 0);
            data_out : OUT signed (15 downto 0)
        );
    end component;
    
    signal wr_en1,wr_en2,wr_en3,wr_en4,wr_en5,wr_en6,wr_en7: STD_LOGIC :='0';
    signal data_out0,data_out1,data_out2,data_out3,data_out4,data_out5,data_out6,data_out7: signed(15 downto 0);
    constant wr_en0:STD_LOGIC:='0';
    
begin

    reg0: reg16bit port map(clk=>clk, rst=>rst, wr_en=>wr_en0, data_in=>dados_write, data_out=>data_out0);
    reg1: reg16bit port map(clk=>clk, rst=>rst, wr_en=>wr_en1, data_in=>dados_write, data_out=>data_out1);
    reg2: reg16bit port map(clk=>clk, rst=>rst, wr_en=>wr_en2, data_in=>dados_write, data_out=>data_out2);
    reg3: reg16bit port map(clk=>clk, rst=>rst, wr_en=>wr_en3, data_in=>dados_write, data_out=>data_out3);
    reg4: reg16bit port map(clk=>clk, rst=>rst, wr_en=>wr_en4, data_in=>dados_write, data_out=>data_out4);
    reg5: reg16bit port map(clk=>clk, rst=>rst, wr_en=>wr_en5, data_in=>dados_write, data_out=>data_out5);
    reg6: reg16bit port map(clk=>clk, rst=>rst, wr_en=>wr_en6, data_in=>dados_write, data_out=>data_out6);
    reg7: reg16bit port map(clk=>clk, rst=>rst, wr_en=>wr_en7, data_in=>dados_write, data_out=>data_out7);
    
    wr_en1<='1' when slt_write = "001" else '0';
    wr_en2<='1' when slt_write = "010" else '0';
    wr_en3<='1' when slt_write = "011" else '0';
    wr_en4<='1' when slt_write = "100" else '0';
    wr_en5<='1' when slt_write = "101" else '0';
    wr_en6<='1' when slt_write = "110" else '0';
    wr_en7<='1' when slt_write = "111" else '0';
    
    dados_read1 <= data_out0 when slt_read1 ="000" else
                    data_out1 when slt_read1 ="001" else
                    data_out2 when slt_read1 ="010" else
                    data_out3 when slt_read1 ="011" else
                    data_out4 when slt_read1 ="100" else
                    data_out5 when slt_read1 ="101" else
                    data_out6 when slt_read1 ="110" else
                    data_out7 when slt_read1 ="111" else
                    "0000000000000000";
    
    dados_read2 <= data_out0 when slt_read2 ="000" else
                    data_out1 when slt_read2 ="001" else
                    data_out2 when slt_read2 ="010" else
                    data_out3 when slt_read2 ="011" else
                    data_out4 when slt_read2 ="100" else
                    data_out5 when slt_read2 ="101" else
                    data_out6 when slt_read2 ="110" else
                    data_out7 when slt_read2 ="111" else
                    "0000000000000000";

end architecture a_bancoreg;

MeuProjeto/ULA.vhd
--Alunos: Jhonny Kristyan Vaz-Tostes de Assis
--        Gabriel Henrique Kwiatkovski Godinho
-- entrega ULA

library ieee;
use ieee.std_logic_1164.all;
use ieee.numeric_std.all;

--------------------
-- 00 = soma
-- 01 = subtração
-- 10 = maior
-- 11 = diferente
--------------------

entity ULA is 
    port(   in_termo_1 : in signed (15 downto 0);
            in_termo_2 : in signed (15 downto 0);

            select_op : in unsigned(1 downto 0);

            out_op_1 : out signed (15 downto 0);
            out_op_2 : out std_logic);
end entity;

architecture a_ULA of ULA is
begin
    out_op_1 <= in_termo_1+in_termo_2 when select_op="00" else
                in_termo_2-in_termo_1 when select_op="01" else
                "0000000000000000";

    out_op_2 <= '1' when select_op="10" and (in_termo_1 > in_termo_2) else
                '1' when select_op="11" and (in_termo_1 /= in_termo_2) else
                '0';

end architecture;

--------------------------------------------------

MeuProjeto/reg17bit.vhd
library IEEE;
use IEEE.std_logic_1164.all;
use IEEE.numeric_std.all;

entity reg17bit is
    port(
        clk :in std_logic;
        rst :in std_logic;
        wr_en: in std_logic;
        data_in: in unsigned(16 downto 0);
        data_out: out unsigned(16 downto 0)
    );
end entity reg17bit;

architecture a_reg17bit of reg17bit is
    signal registro: unsigned(16 downto 0);
begin

   process (clk,rst,wr_en)
   begin
       if rst='1' then
           registro<="00000000000000000";
       elsif wr_en='1' then
           if rising_edge(clk) then
               registro<=data_in;
           end if;
       end if;
   end process;
   
   data_out <= registro;

end architecture a_reg17bit;

MeuProjeto/uni_controle.vhd
library ieee;
use ieee.std_logic_1164.all;
use ieee.numeric_std.all;

entity uni_controle is
    port(
        clk, rst: in std_logic;
        instruction: in unsigned(16 downto 0);
        estado: in unsigned(1 downto 0);
        
        jump_en, pc_read, rom_read: out STD_LOGIC;
        
        regWrite: out STD_LOGIC;
        slt_ula: out unsigned(1 downto 0);
        ALUsrcA: out std_logic;
        slt_reg_read_1, slt_reg_read_2, slt_reg_write: out unsigned(2 downto 0)
        
    );
end entity uni_controle;

architecture a_uni_controle of uni_controle is
    
    signal opcode: unsigned(7 downto 0);

begin

    opcode <= instruction(16 downto 9);
    
    jump_en <= '1' when opcode ="00000110" else '0';
    pc_read <= '1' when estado ="01" else '0';
    rom_read <= '1' when estado ="00" else '0';
    regWrite <= '1' when (opcode = "00000010" or opcode = "00000101") and estado = "10" else '0';
    slt_ula <= "00" when opcode = "00000100" else "00";
    ALUsrcA <= '1' when opcode = "00000011" or opcode = "00000100" else '0';
    slt_reg_read_1 <= instruction(2 downto 0) when opcode ="00000010" else "000" ;
    slt_reg_read_2 <= "001" when opcode="00000010" else "000" ;
    slt_reg_write <="001" when opcode="00000001" else "000" ;
    
end architecture a_uni_controle;

MeuProjeto/ROM.vhd
library ieee;
use ieee.std_logic_1164.all;
use ieee.numeric_std.all;

entity rom is
    port( clk : in std_logic;
        endereco : in unsigned(6 downto 0);--memória de programa = 4Kbytes 4000bytes = 32000 bits
        instr : out unsigned(16 downto 0)    --32000/17=1882 endereços de 17 bits
    );
end entity;

architecture a_rom of rom is
    type mem is array (0 to 127) of unsigned(16 downto 0);--trocar futuramente 127 por 1881
    constant conteudo_rom : mem := (
        -- caso endereco => conteudo
        0 => B"00000001_000000101",
        1 => B"00000010_000000011",
        2 => B"00000001_000001000",
        3 => B"00000010_000000100",
        4 => B"00000011_000000011",
        5 => B"00000100_000000100",
        6 => B"00000010_000000101",
        7 => B"00000011_000000101",
        8 => B"00000101_000000001",
        9 => B"00000010_000000101",
        10=> B"00000110_000010100",
        20=> B"00000011_000000101",
        21=> B"00000010_000000011",
        22=> B"00000110_000000100",
        23=> B"00000000_000000000",
        24=> B"00000000_000000000",
        -- abaixo: casos omissos => (zero em todos os bits)
        others => (others=>'0')
    );

begin
    process(clk)
    begin
        if(rising_edge(clk)) then
        instr <= conteudo_rom(to_integer(endereco));
    end if;
end process;
end architecture;

MeuProjeto/reg7bit.vhd
library IEEE;
use IEEE.std_logic_1164.all;
use IEEE.numeric_std.all;

entity reg7bit is
    port(
        clk :in std_logic;
        rst :in std_logic;
        wr_en: in std_logic;
        data_in: in unsigned(6 downto 0);
        data_out: out unsigned(6 downto 0)
    );
end entity reg7bit;

architecture a_reg7bit of reg7bit is
    signal registro: unsigned(6 downto 0);
begin

   process (clk,rst,wr_en)
   begin
       if rst='1' then
           registro<="0000000";
       elsif wr_en='1' then
           if rising_edge(clk) then
               registro<=data_in;
           end if;
       end if;
   end process;
   
   data_out <= registro;

end architecture a_reg7bit;

MeuProjeto/maquina_de_estados.vhd
library ieee;
use ieee.std_logic_1164.all;
use ieee.numeric_std.all;
entity maquina_de_estados is
    
    port( clk,rst: in std_logic;
        estado: out unsigned(1 downto 0)
    );
end entity;
architecture a_maquina_de_estados of maquina_de_estados is
    signal estado_s: unsigned(1 downto 0);
begin
    process(clk,rst)
    begin
        if rst='1' then
            estado_s <= "00";
        elsif rising_edge(clk) then
            if estado_s="10" then        
                estado_s <= "00";         
            else
                estado_s <= estado_s+1;   
            end if;
        end if;
    end process;
    estado <= estado_s;
end architecture;

MeuProjeto/processador.vhd
library IEEE;
use IEEE.std_logic_1164.all;
use IEEE.numeric_std.all;

entity processador is
    port(
        clk,rst: in STD_LOGIC
    );
end entity processador;

architecture a_processador of processador is
    component maquina_de_estados is
        port
        (
            clk    : IN std_logic ;
            rst    : IN std_logic ;
            estado : OUT unsigned(1 downto 0)
        );
    end component;
    
    component reg7bit is
        port
        (
            clk      : IN std_logic ;
            rst      : IN std_logic ;
            wr_en    : IN std_logic ;
            data_in  : IN unsigned (6 downto 0);
            data_out : OUT unsigned (6 downto 0)
        );
    end component;
    
    component rom is
        port
        (
            clk      : IN std_logic ;
            endereco : IN unsigned (6 downto 0);
            instr    : OUT unsigned (16 downto 0)
        );
    end component;
    
    component uni_controle is
        port
        (
            clk     : IN std_logic ;
            rst     : IN std_logic ;
            instruction  : IN unsigned (16 downto 0);
            jump_en : OUT STD_LOGIC;
            pc_read : out STD_LOGIC;
            estado : in unsigned(1 downto 0);
            rom_read: out STD_LOGIC;
            regWrite: out STD_LOGIC;
            slt_ula: out unsigned(1 downto 0);
            ALUsrcA: out std_logic;
            slt_reg_read_1: out unsigned(2 downto 0);
            slt_reg_read_2: out unsigned(2 downto 0);
            slt_reg_write: out unsigned(2 downto 0)
        );
    end component;
    
    component reg17bit is
        port
        (
            clk      : IN std_logic ;
            rst      : IN std_logic ;
            wr_en    : IN std_logic ;
            data_in  : IN unsigned (16 downto 0);
            data_out : OUT unsigned (16 downto 0)
        );
    end component;
    
    component reg16bit is
        port
        (
            clk      : IN std_logic ;
            rst      : IN std_logic ;
            wr_en    : IN std_logic ;
            data_in  : IN signed (15 downto 0);
            data_out : OUT signed (15 downto 0)
        );
    end component;
    
    component ULA is
        port
        (
            in_termo_1 : IN signed (15 downto 0);
            in_termo_2 : IN signed (15 downto 0);
            select_op  : IN unsigned (1 downto 0);
            out_op_1   : OUT signed (15 downto 0);
            out_op_2   : OUT std_logic
        );
    end component;
    
    component bancoreg is
        port
        (
            slt_read1   : IN unsigned (2 downto 0);
            slt_read2   : IN unsigned (2 downto 0);
            dados_write : IN signed (15 downto 0);
            slt_write   : IN unsigned (2 downto 0);
            wr_en       : IN STD_LOGIC ;
            clk         : IN STD_LOGIC ;
            rst         : IN STD_LOGIC ;
            dados_read1 : OUT signed (15 downto 0);
            dados_read2 : OUT signed (15 downto 0)
        );
    end component;
    
    component mux1x2 is
        port
        (
            slt  : IN std_logic ;
            in0  : IN signed (15 downto 0);
            in1  : IN signed (15 downto 0);
            out0 : OUT signed (15 downto 0)
        );
    end component;
    
    signal estado: unsigned(1 downto 0);
    
    signal pc_read: STD_LOGIC;
    signal pc_in, pc_out: unsigned(6 downto 0);
    
    signal instruction,rom_out,ir_out: unsigned(16 downto 0):= "00000000000000000";
    
    signal jump_en,rom_read: STD_LOGIC;
    
    signal cte: signed(7 downto 0);
    signal regWrite: STD_LOGIC;
    signal slt_ula: unsigned(1 downto 0);
    signal slt_reg_read_1, slt_reg_read_2, slt_reg_write: unsigned(2 downto 0);
    signal ALUsrcA: std_logic;
    
    signal banco_out_1,banco_out_2,regA_out,regB_out,out_mux,out_op_1: signed(15 downto 0);
    signal out_op_2: STD_LOGIC;
    
    signal in1:signed(15 downto 0);
    
begin

    state: maquina_de_estados port map(
        clk => clk,
        rst => rst,
        estado => estado
    );
    
    pc: reg7bit port map(
        clk      =>clk ,
        rst      =>rst ,
        wr_en    =>pc_read ,
        data_in  =>pc_in ,
        data_out =>pc_out
    );
    
    mem_rom: rom port map(
        clk      =>clk,
        endereco =>pc_out,
        instr    =>rom_out
    );
    
    uc: uni_controle port map(
        clk     => clk,
        rst     => rst,
        instruction  =>rom_out,
        jump_en =>jump_en,
        pc_read =>pc_read,
        estado =>estado,
        rom_read=>rom_read,
        regWrite =>regWrite ,
        slt_ula =>slt_ula,
        ALUsrcA =>ALUsrcA,
        slt_reg_read_1=>slt_reg_read_1,
        slt_reg_read_2=>slt_reg_read_2,
        slt_reg_write=>slt_reg_write
    );
    
    ir: reg17bit port map(
        clk      =>clk,
        rst      =>rst,
        wr_en    =>rom_read,
        data_in  =>rom_out,
        data_out =>ir_out
    );
    
    regA: reg16bit port map(
        clk=>clk,
        rst=>rst,
        wr_en=>'1',
        data_in=>banco_out_1,
        data_out=>regA_out
    );
    
    regB: reg16bit port map(
        clk=>clk,
        rst=>rst,
        wr_en=>'1',
        data_in=>banco_out_2,
        data_out=>regB_out
    );
    
    alu: ULA port map(
        in_termo_1=>out_mux,
        in_termo_2=>regB_out,
        select_op=>slt_ula,
        out_op_1=>out_op_1,
        out_op_2=>out_op_2
    );
    
    banco_reg: bancoreg port map(
        slt_read1=>slt_reg_read_1,
        slt_read2=>slt_reg_read_2,
        dados_write=>out_op_1,
        slt_write=>slt_reg_write,
        wr_en=>regWrite,
        clk=>clk,
        rst=>rst,
        dados_read1=>banco_out_1,
        dados_read2=>banco_out_2
    );
    
    mux_regA: mux1x2 port map(
        slt=>ALUsrcA,
        in0=>banco_out_1,
        in1=>in1,
        out0=>out_mux
    );
    
    process (rst, clk)
    begin
        if rst='1' then
            pc_in<="0000000";
        elsif rising_edge(clk) then
            if jump_en = '0' then
                pc_in<=pc_out +1;
            else
                pc_in<=rom_out(6 downto 0);
            end if;
        end if;
    end process;
    
    cte<=signed(ir_out(7 downto 0));
    in1<=signed("00000000" & ir_out(7 downto 0));
    --instruction <= rom_out when estado ="00" else "00000000000000000";

end architecture ;

MeuProjeto/processador_tb.vhd
library IEEE;
use IEEE.std_logic_1164.all;
use IEEE.numeric_std.all;

entity processador_tb is
end entity processador_tb;

architecture a_processador_tb of processador_tb is
    component processador is
        port
        (
            clk : IN STD_LOGIC ;
            rst : IN STD_LOGIC
        );
    end component;
    
    constant period_time : time := 100 ns;
    signal finished : std_logic := '0';
    signal clk, reset : std_logic;
    
begin

    uut: processador port map (
        clk => clk,
        rst => reset
    );
    
    reset_global: process
    begin
        reset <= '1';
        wait for period_time*2; 
        reset <= '0';
        wait;
    end process;
    
    sim_time_proc: process
    begin
        wait for 1800 ns;
        finished <= '1';
        wait;
    end process sim_time_proc;

    clk_proc: process
    begin 
        while finished /= '1' loop
            clk <= '0';
            wait for period_time/2;
            clk <= '1';
            wait for period_time/2;
        end loop;
        wait;
    end process clk_proc;

    process
    begin
        
        wait;
    end process;

end architecture ;

MeuProjeto/processador_tb.vcd
$date
  Thu Nov 18 21:53:34 2021
$end
$version
  GHDL v0
$end
$timescale
  1 fs
$end
$scope module standard $end
$upscope $end
$scope module textio $end
$upscope $end
$scope module std_logic_1164 $end
$upscope $end
$scope module numeric_std $end
$upscope $end
$scope module processador_tb $end
$var reg 1 ! finished $end
$var reg 1 " clk $end
$var reg 1 # reset $end
$scope module uut $end
$var reg 1 $ clk $end
$var reg 1 % rst $end
$var reg 2 & estado[1:0] $end
$var reg 1 ' pc_read $end
$var reg 7 ( pc_in[6:0] $end
$var reg 7 ) pc_out[6:0] $end
$var reg 17 * instruction[16:0] $end
$var reg 17 + rom_out[16:0] $end
$var reg 17 , ir_out[16:0] $end
$var reg 1 - jump_en $end
$var reg 1 . rom_read $end
$var reg 8 / cte[7:0] $end
$var reg 1 0 regwrite $end
$var reg 2 1 slt_ula[1:0] $end
$var reg 3 2 slt_reg_read_1[2:0] $end
$var reg 3 3 slt_reg_read_2[2:0] $end
$var reg 3 4 slt_reg_write[2:0] $end
$var reg 1 5 alusrca $end
$var reg 16 6 banco_out_1[15:0] $end
$var reg 16 7 banco_out_2[15:0] $end
$var reg 16 8 rega_out[15:0] $end
$var reg 16 9 regb_out[15:0] $end
$var reg 16 : out_mux[15:0] $end
$var reg 16 ; out_op_1[15:0] $end
$var reg 1 < out_op_2 $end
$var reg 16 = in1[15:0] $end
$scope module state $end
$var reg 1 > clk $end
$var reg 1 ? rst $end
$var reg 2 @ estado[1:0] $end
$var reg 2 A estado_s[1:0] $end
$upscope $end
$scope module pc $end
$var reg 1 B clk $end
$var reg 1 C rst $end
$var reg 1 D wr_en $end
$var reg 7 E data_in[6:0] $end
$var reg 7 F data_out[6:0] $end
$var reg 7 G registro[6:0] $end
$upscope $end
$scope module mem_rom $end
$var reg 1 H clk $end
$var reg 7 I endereco[6:0] $end
$var reg 17 J instr[16:0] $end
$upscope $end
$scope module uc $end
$var reg 1 K clk $end
$var reg 1 L rst $end
$var reg 17 M instruction[16:0] $end
$var reg 2 N estado[1:0] $end
$var reg 1 O jump_en $end
$var reg 1 P pc_read $end
$var reg 1 Q rom_read $end
$var reg 1 R regwrite $end
$var reg 2 S slt_ula[1:0] $end
$var reg 1 T alusrca $end
$var reg 3 U slt_reg_read_1[2:0] $end
$var reg 3 V slt_reg_read_2[2:0] $end
$var reg 3 W slt_reg_write[2:0] $end
$var reg 8 X opcode[7:0] $end
$upscope $end
$scope module ir $end
$var reg 1 Y clk $end
$var reg 1 Z rst $end
$var reg 1 [ wr_en $end
$var reg 17 \ data_in[16:0] $end
$var reg 17 ] data_out[16:0] $end
$var reg 17 ^ registro[16:0] $end
$upscope $end
$scope module rega $end
$var reg 1 _ clk $end
$var reg 1 ` rst $end
$var reg 1 a wr_en $end
$var reg 16 b data_in[15:0] $end
$var reg 16 c data_out[15:0] $end
$var reg 16 d registro[15:0] $end
$upscope $end
$scope module regb $end
$var reg 1 e clk $end
$var reg 1 f rst $end
$var reg 1 g wr_en $end
$var reg 16 h data_in[15:0] $end
$var reg 16 i data_out[15:0] $end
$var reg 16 j registro[15:0] $end
$upscope $end
$scope module alu $end
$var reg 16 k in_termo_1[15:0] $end
$var reg 16 l in_termo_2[15:0] $end
$var reg 2 m select_op[1:0] $end
$var reg 16 n out_op_1[15:0] $end
$var reg 1 o out_op_2 $end
$upscope $end
$scope module banco_reg $end
$var reg 3 p slt_read1[2:0] $end
$var reg 3 q slt_read2[2:0] $end
$var reg 16 r dados_write[15:0] $end
$var reg 3 s slt_write[2:0] $end
$var reg 1 t wr_en $end
$var reg 1 u clk $end
$var reg 1 v rst $end
$var reg 16 w dados_read1[15:0] $end
$var reg 16 x dados_read2[15:0] $end
$var reg 1 y wr_en1 $end
$var reg 1 z wr_en2 $end
$var reg 1 { wr_en3 $end
$var reg 1 | wr_en4 $end
$var reg 1 } wr_en5 $end
$var reg 1 !" wr_en6 $end
$var reg 1 "" wr_en7 $end
$var reg 16 #" data_out0[15:0] $end
$var reg 16 $" data_out1[15:0] $end
$var reg 16 %" data_out2[15:0] $end
$var reg 16 &" data_out3[15:0] $end
$var reg 16 '" data_out4[15:0] $end
$var reg 16 (" data_out5[15:0] $end
$var reg 16 )" data_out6[15:0] $end
$var reg 16 *" data_out7[15:0] $end
$scope module reg0 $end
$var reg 1 +" clk $end
$var reg 1 ," rst $end
$var reg 1 -" wr_en $end
$var reg 16 ." data_in[15:0] $end
$var reg 16 /" data_out[15:0] $end
$var reg 16 0" registro[15:0] $end
$upscope $end
$scope module reg1 $end
$var reg 1 1" clk $end
$var reg 1 2" rst $end
$var reg 1 3" wr_en $end
$var reg 16 4" data_in[15:0] $end
$var reg 16 5" data_out[15:0] $end
$var reg 16 6" registro[15:0] $end
$upscope $end
$scope module reg2 $end
$var reg 1 7" clk $end
$var reg 1 8" rst $end
$var reg 1 9" wr_en $end
$var reg 16 :" data_in[15:0] $end
$var reg 16 ;" data_out[15:0] $end
$var reg 16 <" registro[15:0] $end
$upscope $end
$scope module reg3 $end
$var reg 1 =" clk $end
$var reg 1 >" rst $end
$var reg 1 ?" wr_en $end
$var reg 16 @" data_in[15:0] $end
$var reg 16 A" data_out[15:0] $end
$var reg 16 B" registro[15:0] $end
$upscope $end
$scope module reg4 $end
$var reg 1 C" clk $end
$var reg 1 D" rst $end
$var reg 1 E" wr_en $end
$var reg 16 F" data_in[15:0] $end
$var reg 16 G" data_out[15:0] $end
$var reg 16 H" registro[15:0] $end
$upscope $end
$scope module reg5 $end
$var reg 1 I" clk $end
$var reg 1 J" rst $end
$var reg 1 K" wr_en $end
$var reg 16 L" data_in[15:0] $end
$var reg 16 M" data_out[15:0] $end
$var reg 16 N" registro[15:0] $end
$upscope $end
$scope module reg6 $end
$var reg 1 O" clk $end
$var reg 1 P" rst $end
$var reg 1 Q" wr_en $end
$var reg 16 R" data_in[15:0] $end
$var reg 16 S" data_out[15:0] $end
$var reg 16 T" registro[15:0] $end
$upscope $end
$scope module reg7 $end
$var reg 1 U" clk $end
$var reg 1 V" rst $end
$var reg 1 W" wr_en $end
$var reg 16 X" data_in[15:0] $end
$var reg 16 Y" data_out[15:0] $end
$var reg 16 Z" registro[15:0] $end
$upscope $end
$upscope $end
$scope module mux_rega $end
$var reg 1 [" slt $end
$var reg 16 \" in0[15:0] $end
$var reg 16 ]" in1[15:0] $end
$var reg 16 ^" out0[15:0] $end
$upscope $end
$upscope $end
$upscope $end
$enddefinitions $end
#0
0!
0"
1#
0$
1%
b00 &
0'
b0000000 (
b0000000 )
b00000000000000000 *
bUUUUUUUUUUUUUUUUU +
b00000000000000000 ,
0-
1.
b00000000 /
00
b00 1
b000 2
b000 3
b000 4
05
b0000000000000000 6
b0000000000000000 7
b0000000000000000 8
b0000000000000000 9
b0000000000000000 :
b0000000000000000 ;
0<
b0000000000000000 =
0>
1?
b00 @
b00 A
0B
1C
0D
b0000000 E
b0000000 F
b0000000 G
0H
b0000000 I
bUUUUUUUUUUUUUUUUU J
0K
1L
bUUUUUUUUUUUUUUUUU M
b00 N
0O
0P
1Q
0R
b00 S
0T
b000 U
b000 V
b000 W
bUUUUUUUU X
0Y
1Z
1[
bUUUUUUUUUUUUUUUUU \
b00000000000000000 ]
b00000000000000000 ^
0_
1`
1a
b0000000000000000 b
b0000000000000000 c
b0000000000000000 d
0e
1f
1g
b0000000000000000 h
b0000000000000000 i
b0000000000000000 j
b0000000000000000 k
b0000000000000000 l
b00 m
b0000000000000000 n
0o
b000 p
b000 q
b0000000000000000 r
b000 s
0t
0u
1v
b0000000000000000 w
b0000000000000000 x
0y
0z
0{
0|
0}
0!"
0""
b0000000000000000 #"
b0000000000000000 $"
b0000000000000000 %"
b0000000000000000 &"
b0000000000000000 '"
b0000000000000000 ("
b0000000000000000 )"
b0000000000000000 *"
0+"
1,"
0-"
b0000000000000000 ."
b0000000000000000 /"
b0000000000000000 0"
01"
12"
03"
b0000000000000000 4"
b0000000000000000 5"
b0000000000000000 6"
07"
18"
09"
b0000000000000000 :"
b0000000000000000 ;"
b0000000000000000 <"
0="
1>"
0?"
b0000000000000000 @"
b0000000000000000 A"
b0000000000000000 B"
0C"
1D"
0E"
b0000000000000000 F"
b0000000000000000 G"
b0000000000000000 H"
0I"
1J"
0K"
b0000000000000000 L"
b0000000000000000 M"
b0000000000000000 N"
0O"
1P"
0Q"
b0000000000000000 R"
b0000000000000000 S"
b0000000000000000 T"
0U"
1V"
0W"
b0000000000000000 X"
b0000000000000000 Y"
b0000000000000000 Z"
0["
b0000000000000000 \"
b0000000000000000 ]"
b0000000000000000 ^"
#50000000
1"
1$
b00000001000000011 +
b001 4
15
1>
1B
1H
b00000001000000011 J
1K
b00000001000000011 M
1T
b001 W
b00000001 X
1Y
b00000001000000011 \
1_
1e
b001 s
1u
1+"
11"
17"
1="
1C"
1I"
1O"
1U"
1["
#100000000
0"
0$
0>
0B
0H
0K
0Y
0_
0e
0u
0+"
01"
07"
0="
0C"
0I"
0O"
0U"
#150000000
1"
1$
1>
1B
1H
1K
1Y
1_
1e
1u
1+"
11"
17"
1="
1C"
1I"
1O"
1U"
#200000000
0"
0#
0$
0%
0>
0?
0B
0C
0H
0K
0L
0Y
0Z
0_
0`
0e
0f
0u
0v
0+"
0,"
01"
02"
07"
08"
0="
0>"
0C"
0D"
0I"
0J"
0O"
0P"
0U"
0V"
#250000000
1"
1$
b01 &
1'
b0000001 (
b00000001000000011 ,
0.
b00000011 /
b0000000000000011 :
b0000000000000011 ;
b0000000000000011 =
1>
b01 @
b01 A
1B
1D
b0000001 E
1H
1K
b01 N
1P
0Q
1Y
0[
b00000001000000011 ]
b00000001000000011 ^
1_
1e
b0000000000000011 k
b0000000000000011 n
b0000000000000011 r
1u
1+"
b0000000000000011 ."
11"
b0000000000000011 4"
17"
b0000000000000011 :"
1="
b0000000000000011 @"
1C"
b0000000000000011 F"
1I"
b0000000000000011 L"
1O"
b0000000000000011 R"
1U"
b0000000000000011 X"
b0000000000000011 ]"
b0000000000000011 ^"
#300000000
0"
0$
0>
0B
0H
0K
0Y
0_
0e
0u
0+"
01"
07"
0="
0C"
0I"
0O"
0U"
#350000000
1"
1$
b10 &
0'
b0000001 )
10
1>
b10 @
b10 A
1B
0D
b0000001 F
b0000001 G
1H
b0000001 I
1K
b10 N
0P
1R
1Y
1_
1e
1t
1u
1y
1+"
11"
13"
17"
1="
1C"
1I"
1O"
1U"
#400000000
0"
0$
0>
0B
0H
0K
0Y
0_
0e
0u
0+"
01"
07"
0="
0C"
0I"
0O"
0U"
#450000000
1"
1$
b00 &
b0000010 (
b00000000000000011 +
1.
00
b000 4
05
b0000000000000000 :
b0000000000000000 ;
1>
b00 @
b00 A
1B
b0000010 E
1H
b00000000000000011 J
1K
b00000000000000011 M
b00 N
1Q
0R
0T
b000 W
b00000000 X
1Y
1[
b00000000000000011 \
1_
1e
b0000000000000000 k
b0000000000000000 n
b0000000000000000 r
b000 s
0t
1u
0y
b0000000000000011 $"
1+"
b0000000000000000 ."
11"
03"
b0000000000000000 4"
b0000000000000011 5"
b0000000000000011 6"
17"
b0000000000000000 :"
1="
b0000000000000000 @"
1C"
b0000000000000000 F"
1I"
b0000000000000000 L"
1O"
b0000000000000000 R"
1U"
b0000000000000000 X"
0["
b0000000000000000 ^"
#500000000
0"
0$
0>
0B
0H
0K
0Y
0_
0e
0u
0+"
01"
07"
0="
0C"
0I"
0O"
0U"
#550000000
1"
1$
b01 &
1'
b00000000000000011 ,
0.
1>
b01 @
b01 A
1B
1D
1H
1K
b01 N
1P
0Q
1Y
0[
b00000000000000011 ]
b00000000000000011 ^
1_
1e
1u
1+"
11"
17"
1="
1C"
1I"
1O"
1U"
#600000000
0"
0$
0>
0B
0H
0K
0Y
0_
0e
0u
0+"
01"
07"
0="
0C"
0I"
0O"
0U"
#650000000
1"
1$
b10 &
0'
b0000010 )
1>
b10 @
b10 A
1B
0D
b0000010 F
b0000010 G
1H
b0000010 I
1K
b10 N
0P
1Y
1_
1e
1u
1+"
11"
17"
1="
1C"
1I"
1O"
1U"
#700000000
0"
0$
0>
0B
0H
0K
0Y
0_
0e
0u
0+"
01"
07"
0="
0C"
0I"
0O"
0U"
#750000000
1"
1$
b00 &
b0000011 (
b00000000000000110 +
1.
1>
b00 @
b00 A
1B
b0000011 E
1H
b00000000000000110 J
1K
b00000000000000110 M
b00 N
1Q
1Y
1[
b00000000000000110 \
1_
1e
1u
1+"
11"
17"
1="
1C"
1I"
1O"
1U"
#800000000
0"
0$
0>
0B
0H
0K
0Y
0_
0e
0u
0+"
01"
07"
0="
0C"
0I"
0O"
0U"
#850000000
1"
1$
b01 &
1'
b00000000000000110 ,
0.
b00000110 /
b0000000000000110 =
1>
b01 @
b01 A
1B
1D
1H
1K
b01 N
1P
0Q
1Y
0[
b00000000000000110 ]
b00000000000000110 ^
1_
1e
1u
1+"
11"
17"
1="
1C"
1I"
1O"
1U"
b0000000000000110 ]"
#900000000
0"
0$
0>
0B
0H
0K
0Y
0_
0e
0u
0+"
01"
07"
0="
0C"
0I"
0O"
0U"
#950000000
1"
1$
b10 &
0'
b0000011 )
1>
b10 @
b10 A
1B
0D
b0000011 F
b0000011 G
1H
b0000011 I
1K
b10 N
0P
1Y
1_
1e
1u
1+"
11"
17"
1="
1C"
1I"
1O"
1U"
#1000000000
0"
0$
0>
0B
0H
0K
0Y
0_
0e
0u
0+"
01"
07"
0="
0C"
0I"
0O"
0U"
#1050000000
1"
1$
b00 &
b0000100 (
b00000000000000000 +
1.
1>
b00 @
b00 A
1B
b0000100 E
1H
b00000000000000000 J
1K
b00000000000000000 M
b00 N
1Q
1Y
1[
b00000000000000000 \
1_
1e
1u
1+"
11"
17"
1="
1C"
1I"
1O"
1U"
#1100000000
0"
0$
0>
0B
0H
0K
0Y
0_
0e
0u
0+"
01"
07"
0="
0C"
0I"
0O"
0U"
#1150000000
1"
1$
b01 &
1'
b00000000000000000 ,
0.
b00000000 /
b0000000000000000 =
1>
b01 @
b01 A
1B
1D
1H
1K
b01 N
1P
0Q
1Y
0[
b00000000000000000 ]
b00000000000000000 ^
1_
1e
1u
1+"
11"
17"
1="
1C"
1I"
1O"
1U"
b0000000000000000 ]"
