MeuProjeto/ROM.vhd
library ieee;
use ieee.std_logic_1164.all;
use ieee.numeric_std.all;

entity rom is
    port( clk : in std_logic;
        endereco : in unsigned(6 downto 0);--memória de programa = 4Kbytes 4000bytes = 32000 bits
        dado : out signed(16 downto 0)    --32000/17=1882 endereços de 17 bits
    );
end entity;

architecture a_rom of rom is
    type mem is array (0 to 127) of signed(16 downto 0);--trocar futuramente 127 por 1881
    constant conteudo_rom : mem := (
        -- caso endereco => conteudo
        0 => "00000000000001000",
        1 => "00000000000000111",
        2 => "00000000000000100",
        -- abaixo: casos omissos => (zero em todos os bits)
        others => (others=>'0')
    );

begin
   process(clk)
   begin
      if(rising_edge(clk)) then
         dado <= conteudo_rom(to_integer(endereco));
      end if;
   end process;
end architecture;

MeuProjeto/ROM_tb.vhd
library ieee;
use ieee.std_logic_1164.all;
use ieee.numeric_std.all;

entity ROM_tb is 
end;

architecture a_ROM_tb of ROM_tb is
    component ROM
        port(   clk : in std_logic;
                endereco : in unsigned(6 downto 0);--memória de programa = 4Kbytes 4000bytes = 32000 bits
                dado : out signed(16 downto 0)    --32000/17=1882 endereços de 17 bits
            );
    end component;

    signal endereco : unsigned(6 downto 0);
    signal dado : signed(16 downto 0);

    constant period_time : time := 100 ns;
    signal finished : std_logic := '0';
    signal clk, reset : std_logic;

    begin
        uut: ROM port map(  clk=>clk,
                            endereco=>endereco,
                            dado=>dado
                        );


    reset_global: process
    begin
        reset <= '1';
        wait for period_time*2; -- espera 2 clocks, pra garantir
        reset <= '0';
        wait;
    end process;
  
    sim_time_proc: process
    begin
        wait for 700 ns;
        finished <= '1';
        wait;
    end process sim_time_proc;

    clk_proc: process
    begin -- gera clock até que sim_time_proc termine
        while finished /= '1' loop
        clk <= '0';
        wait for period_time/2;
        clk <= '1';
        wait for period_time/2;
        end loop;
        wait;
    end process clk_proc;  

    process 
    begin
        wait for 200 ns;
       
        endereco <= "0000000";
        wait for 100 ns;

        endereco <= "0000001";
        wait for 100 ns;

        endereco <= "0000010";
        wait for 100 ns;

        endereco <= "0000111";
        wait for 100 ns;

        endereco <= "1000111";
        wait;
    end process;
    end architecture a_ROM_tb;

MeuProjeto/ROM_tb.vcd
$date
  Thu Nov 11 20:16:23 2021
$end
$version
  GHDL v0
$end
$timescale
  1 fs
$end
$scope module standard $end
$upscope $end
$scope module std_logic_1164 $end
$upscope $end
$scope module numeric_std $end
$upscope $end
$scope module rom_tb $end
$var reg 7 ! endereco[6:0] $end
$var reg 17 " dado[16:0] $end
$var reg 1 # finished $end
$var reg 1 $ clk $end
$var reg 1 % reset $end
$scope module uut $end
$var reg 1 & clk $end
$var reg 7 ' endereco[6:0] $end
$var reg 17 ( dado[16:0] $end
$upscope $end
$upscope $end
$enddefinitions $end
#0
bUUUUUUU !
bUUUUUUUUUUUUUUUUU "
0#
0$
1%
0&
bUUUUUUU '
bUUUUUUUUUUUUUUUUU (
#50000000
b00000000000001000 "
1$
1&
b00000000000001000 (
#100000000
0$
0&
#150000000
1$
1&
#200000000
b0000000 !
0$
0%
0&
b0000000 '
#250000000
1$
1&
#300000000
b0000001 !
0$
0&
b0000001 '
#350000000
b00000000000000111 "
1$
1&
b00000000000000111 (
#400000000
b0000010 !
0$
0&
b0000010 '
#450000000
b00000000000000100 "
1$
1&
b00000000000000100 (
#500000000
b0000111 !
0$
0&
b0000111 '
#550000000
b00000000000000000 "
1$
1&
b00000000000000000 (
#600000000
b1000111 !
0$
0&
b1000111 '
#650000000
1$
1&
#700000000
1#
0$
0&
