MeuProjeto/ULA.vhd
--Alunos: Jhonny Kristyan Vaz-Tostes de Assis
--        Gabriel Henrique Kwiatkovski Godinho
-- entrega ULA

library ieee;
use ieee.std_logic_1164.all;
use ieee.numeric_std.all;

--------------------
-- 00 = soma
-- 01 = subtração
-- 10 = maior
-- 11 = diferente
--------------------

entity ULA is 
    port(   in_termo_1 : in signed (15 downto 0);
            in_termo_2 : in signed (15 downto 0);

            select_op : in unsigned(1 downto 0);

            out_op_1 : out signed (15 downto 0);
            out_op_2 : out std_logic);
end entity;

architecture a_ULA of ULA is
begin
    out_op_1 <= in_termo_1+in_termo_2 when select_op="00" else
                in_termo_2-in_termo_1 when select_op="01" else
                "0000000000000000";

    out_op_2 <= '1' when select_op="10" and (in_termo_1 > in_termo_2) else
                '1' when select_op="11" and (in_termo_1 /= in_termo_2) else
                '0';

end architecture;

--------------------------------------------------

MeuProjeto/ULA_tb.vhd
--Alunos: Jhonny Kristyan Vaz-Tostes de Assis
--        Gabriel Henrique Kwiatkovski Godinho
-- entrega ULA

library ieee;
use ieee.std_logic_1164.all;
use ieee.numeric_std.all;

--------------------
-- 00 = soma
-- 01 = subtração
-- 10 = maior
-- 11 = diferente
--------------------

entity ULA_tb is 
end;

architecture a_ULA_tb of ULA_tb is
    component ULA
        port(   in_termo_1 : in signed (15 downto 0);
                in_termo_2 : in signed (15 downto 0);

                select_op : unsigned(1 downto 0);
                

                out_op_1 : out signed (15 downto 0);
                out_op_2 : out std_logic);
    end component;

    signal in_termo_1, in_termo_2 : signed (15 downto 0);
    signal select_op : unsigned(1 downto 0);
    signal out_op_1 : signed (15 downto 0);
    signal out_op_2 : std_logic;

    begin
        uut: ULA port map(  in_termo_1=>in_termo_1,
                            in_termo_2=>in_termo_2,
                            select_op=>select_op,
                            out_op_1=>out_op_1,
                            out_op_2=>out_op_2
                            );
    
    process                        
    begin 
    --testes de soma-----------------------
        --soma normal
        in_termo_1 <= "0010101100100000";
        in_termo_2 <= "0000000010000011";
        select_op <= "00";

        wait for 50 ns;
    
        --soma com número negativo
        in_termo_1 <= "0100001100001001";
        in_termo_2 <= "1111111111111101";
        select_op <= "00";
        wait for 50 ns;  
       
    --testes de subtração------------------
        --subtraindo número menor do maior
        in_termo_1 <= "0001001010001001";
        in_termo_2 <= "0000000000000011";
        select_op <= "01";
  
        wait for 50 ns;
        --subtraindo número igual
        in_termo_1 <= "0001101100100000";
        in_termo_2 <= "0001101100100000";
        select_op <= "01";

        wait for 50 ns;
        --subtraindo número maior do menor, o resultado é dado em complemeto de 2
        in_termo_1 <= "0000011111111111";
        in_termo_2 <= "0000100000000000";
        select_op <= "01";
 
        wait for 50 ns;
        --subtração com primeiro termo negativo
        in_termo_1 <= "1001101100100000";
        in_termo_2 <= "0000001100100000";
        select_op <= "01";

        wait for 50 ns;
        --subtração com segundo termo negativo
        in_termo_1 <= "0000000000000001";
        in_termo_2 <= "1111111111111101";
        select_op <= "01";

        wait for 50 ns;

    --testes para ver se termo_1>termo_2---
        --termo_1>termo_2, ambos positivos
        in_termo_1 <= "0001001100100000";
        in_termo_2 <= "0000000010000011";
        select_op <= "10";

        wait for 50 ns;
        --termo_1>termo_2, ambos negativos
        in_termo_1 <= "1100001110000010";
        in_termo_2 <= "1000000000000011";
        select_op <= "10";
        wait for 50 ns;
        --termo_1>termo_2, primeiro positivo e segundo negativo
        in_termo_1 <= "0100001110000010";
        in_termo_2 <= "1000000000000011";
        select_op <= "10";
        wait for 50 ns;
        --termo_1=termo_2
        in_termo_1 <= "0000001100100010";
        in_termo_2 <= "0000001100100010";
        select_op <= "10";
        wait for 50 ns;
        --termo_1<termo_2, ambos positivos
        in_termo_1 <= "0001001100100000";
        in_termo_2 <= "0010000010000011";
        select_op <= "10";
        wait for 50 ns;
        --termo_1<termo_2, ambos negativos
        in_termo_1 <= "1000001110000010";
        in_termo_2 <= "1100000000000011";
        select_op <= "10";
        wait for 50 ns;
        --termo_1<termo2, primeiro negativo e segundo positivo
        in_termo_1 <= "1000001100100010";
        in_termo_2 <= "0000001100100010";
        select_op <= "10";
        wait for 50 ns;

    --testes para ver se termo_1!=termo_2---    
        --termo_1!=termo2
        in_termo_1 <= "0000110000100000";
        in_termo_1 <= "0000000010000011";
        select_op <= "11";
        
        wait for 50 ns;
        --termo_=termo2
        in_termo_1 <= "0100001110000010";
        in_termo_2 <= "0100001110000010";
        select_op <= "11";
        wait for 50 ns;    

        wait;
    end process;
end architecture a_ULA_tb;

MeuProjeto/ULA_tb.vcd
$date
  Fri Nov 05 14:13:54 2021
$end
$version
  GHDL v0
$end
$timescale
  1 fs
$end
$scope module standard $end
$upscope $end
$scope module std_logic_1164 $end
$upscope $end
$scope module numeric_std $end
$upscope $end
$scope module ula_tb $end
$var reg 16 ! in_termo_1[15:0] $end
$var reg 16 " in_termo_2[15:0] $end
$var reg 2 # select_op[1:0] $end
$var reg 16 $ out_op_1[15:0] $end
$var reg 1 % out_op_2 $end
$scope module uut $end
$var reg 16 & in_termo_1[15:0] $end
$var reg 16 ' in_termo_2[15:0] $end
$var reg 2 ( select_op[1:0] $end
$var reg 16 ) out_op_1[15:0] $end
$var reg 1 * out_op_2 $end
$upscope $end
$upscope $end
$enddefinitions $end
#0
b0010101100100000 !
b0000000010000011 "
b00 #
b0010101110100011 $
0%
b0010101100100000 &
b0000000010000011 '
b00 (
b0010101110100011 )
0*
#50000000
b0100001100001001 !
b1111111111111101 "
b0100001100000110 $
b0100001100001001 &
b1111111111111101 '
b0100001100000110 )
#100000000
b0001001010001001 !
b0000000000000011 "
b01 #
b0001001010000110 $
b0001001010001001 &
b0000000000000011 '
b01 (
b0001001010000110 )
#150000000
b0001101100100000 !
b0001101100100000 "
b0000000000000000 $
b0001101100100000 &
b0001101100100000 '
b0000000000000000 )
#200000000
b0000011111111111 !
b0000100000000000 "
b1111111111111111 $
b0000011111111111 &
b0000100000000000 '
b1111111111111111 )
#250000000
b1001101100100000 !
b0000001100100000 "
b1001100000000000 $
b1001101100100000 &
b0000001100100000 '
b1001100000000000 )
#300000000
b0000000000000001 !
b1111111111111101 "
b0000000000000100 $
b0000000000000001 &
b1111111111111101 '
b0000000000000100 )
#350000000
b0001001100100000 !
b0000000010000011 "
b10 #
b0000000000000000 $
1%
b0001001100100000 &
b0000000010000011 '
b10 (
b0000000000000000 )
1*
#400000000
b1100001110000010 !
b1000000000000011 "
b1100001110000010 &
b1000000000000011 '
#450000000
b0100001110000010 !
b0100001110000010 &
#500000000
b0000001100100010 !
b0000001100100010 "
0%
b0000001100100010 &
b0000001100100010 '
0*
#550000000
b0001001100100000 !
b0010000010000011 "
b0001001100100000 &
b0010000010000011 '
#600000000
b1000001110000010 !
b1100000000000011 "
b1000001110000010 &
b1100000000000011 '
#650000000
b1000001100100010 !
b0000001100100010 "
b1000001100100010 &
b0000001100100010 '
#700000000
b0000000010000011 !
b11 #
1%
b0000000010000011 &
b11 (
1*
#750000000
b0100001110000010 !
b0100001110000010 "
0%
b0100001110000010 &
b0100001110000010 '
0*
