MeuProjeto/ROM.vhd
library ieee;
use ieee.std_logic_1164.all;
use ieee.numeric_std.all;

entity rom is
    port( clk : in std_logic;
        endereco : in unsigned(6 downto 0);--memória de programa = 4Kbytes 4000bytes = 32000 bits
        instr : out unsigned(16 downto 0)    --32000/17=1882 endereços de 17 bits
    );
end entity;

architecture a_rom of rom is
    type mem is array (0 to 127) of unsigned(16 downto 0);--trocar futuramente 127 por 1881
    constant conteudo_rom : mem := (
        -- caso endereco => conteudo
        0 => "00000011000010101",
        1 => "00000011000010101",
        2 => "00000011000000110",
        6 => "00000000000000001",
        7 => "00000000000000111",
        21=> "00000000000000100",
        22=> "00000011000000010",
        -- abaixo: casos omissos => (zero em todos os bits)
        others => (others=>'0')
    );

begin
   process(clk)
   begin
      if(rising_edge(clk)) then
         instr <= conteudo_rom(to_integer(endereco));
      end if;
   end process;
end architecture;

MeuProjeto/reg7bit.vhd
library IEEE;
use IEEE.std_logic_1164.all;
use IEEE.numeric_std.all;

entity reg7bit is
    port(
        clk :in std_logic;
        rst :in std_logic;
        wr_en: in std_logic;
        data_in: in unsigned(6 downto 0);
        data_out: out unsigned(6 downto 0)
    );
end entity reg7bit;

architecture a_reg7bit of reg7bit is
    signal registro: unsigned(6 downto 0);
begin

   process (clk,rst,wr_en)
   begin
       if rst='1' then
           registro<="0000000";
       elsif wr_en='1' then
           if rising_edge(clk) then
               registro<=data_in;
           end if;
       end if;
   end process;
   
   data_out <= registro;

end architecture a_reg7bit;

MeuProjeto/maquina_de_estados.vhd
library ieee;
use ieee.std_logic_1164.all;
use ieee.numeric_std.all;

entity maquina_de_estados is
    port(
        clk: in std_logic;
        rst: in std_logic;
        estado: out std_logic
    );
end entity maquina_de_estados;

architecture a_maquina_de_estados of maquina_de_estados is 
    signal estado_s: std_logic;

    begin
    process (clk, rst)
    begin
        if rst = '1' then estado_s<='0';
        elsif rising_edge(clk) then
            estado_s <= not estado_s;
        end if;
    end process;
    estado <= estado_s;

end architecture a_maquina_de_estados;

MeuProjeto/uni_controle.vhd
library ieee;
use ieee.std_logic_1164.all;
use ieee.numeric_std.all;

entity uni_controle is
    port(
        clk, rst: in std_logic;
        top_lvl: out unsigned(16 downto 0)
        
    );
end entity uni_controle;

architecture a_uni_controle of uni_controle is
    component reg7bit is
        port(
            clk :in std_logic;
            rst :in std_logic;
            wr_en: in std_logic;
            data_in: in unsigned(6 downto 0);
            data_out: out unsigned(6 downto 0)
        );
    end component;

    component ROM is
        port( clk : in std_logic;
            endereco : in unsigned(6 downto 0);--memória de programa = 4Kbytes 4000bytes = 32000 bits
            instr : out unsigned(16 downto 0)    --32000/17=1882 endereços de 17 bits
        );
    end component;

    component maquina_de_estados is
        port(
            clk: in std_logic;
            rst: in std_logic;
            estado: out std_logic
        );
    end component;

    signal PC_i,PC_o: unsigned(6 downto 0):="0000000";
    signal estado_maq,wr_en: std_logic;
    signal instr: unsigned(16 downto 0);
    signal opcode: unsigned(7 downto 0);
    signal jump_en: std_logic:='0';

begin
    process (rst, clk, estado_maq)
    begin
        if rst='1' then
            PC_i<="0000000";
            elsif rising_edge(clk) then
                if jump_en='1' then
                    PC_i<=instr(6 downto 0);
                else
                    PC_i<=PC_o +1;
                end if;
            end if;
    end process;
    
    ME1: maquina_de_estados port map(    clk=>clk,
        rst=>rst,
        estado=>estado_maq
    );
    
    PC1: reg7bit port map( clk=>clk,
        rst=>rst,
        wr_en=>wr_en,
        data_in=>PC_i,
        data_out=>PC_o
    );
    
    ROM1: ROM port map(  clk=>clk,
        endereco=>PC_i,
        instr=>instr
    );
    
    top_lvl <= instr when estado_maq='0' else
                "00000000000000000";
    
    opcode<=instr(16 downto 9);
    
    wr_en<= '1' when estado_maq ='1' else
            '0';
    
    jump_en <= '1' when opcode ="00000011" else
    '0';
    
end architecture a_uni_controle;

MeuProjeto/uni_controle_tb.vhd
library ieee;
use ieee.std_logic_1164.all;
use ieee.numeric_std.all;

entity uni_controle_tb is
end entity uni_controle_tb;

architecture a_uni_controle_tb of uni_controle_tb is
    component uni_controle
    port(
        clk :in std_logic;
        rst :in std_logic;
        top_lvl: out unsigned(16 downto 0)
        
    );
end component;

constant period_time : time := 100 ns;
signal finished : std_logic := '0';
signal clk, reset : std_logic;
signal top_lvl: unsigned(16 downto 0);

begin
    uut: uni_controle port map(
        clk=>clk,
        rst=>reset,
        top_lvl=>top_lvl
    );

    reset_global: process
    begin
        reset <= '1';
        wait for period_time*2; -- espera 2 clocks, pra garantir
        reset <= '0';
        wait;
    end process;
    
    sim_time_proc: process
    begin
        wait for 1400 ns;
        finished <= '1';
        wait;
    end process sim_time_proc;

    clk_proc: process
    begin -- gera clock até que sim_time_proc termine
        while finished /= '1' loop
            clk <= '0';
            wait for period_time/2;
            clk <= '1';
            wait for period_time/2;
        end loop;
        wait;
    end process clk_proc;

    process
    begin
        wait for 200 ns;

        wait;
    end process;

end architecture a_uni_controle_tb;

MeuProjeto/uni_controle_tb.vcd
$date
  Mon Nov 15 18:00:44 2021
$end
$version
  GHDL v0
$end
$timescale
  1 fs
$end
$scope module standard $end
$upscope $end
$scope module textio $end
$upscope $end
$scope module std_logic_1164 $end
$upscope $end
$scope module numeric_std $end
$upscope $end
$scope module uni_controle_tb $end
$var reg 1 ! finished $end
$var reg 1 " clk $end
$var reg 1 # reset $end
$var reg 17 $ top_lvl[16:0] $end
$scope module uut $end
$var reg 1 % clk $end
$var reg 1 & rst $end
$var reg 17 ' top_lvl[16:0] $end
$var reg 7 ( pc_i[6:0] $end
$var reg 7 ) pc_o[6:0] $end
$var reg 1 * estado_maq $end
$var reg 1 + wr_en $end
$var reg 17 , instr[16:0] $end
$var reg 8 - opcode[7:0] $end
$var reg 1 . jump_en $end
$scope module me1 $end
$var reg 1 / clk $end
$var reg 1 0 rst $end
$var reg 1 1 estado $end
$var reg 1 2 estado_s $end
$upscope $end
$scope module pc1 $end
$var reg 1 3 clk $end
$var reg 1 4 rst $end
$var reg 1 5 wr_en $end
$var reg 7 6 data_in[6:0] $end
$var reg 7 7 data_out[6:0] $end
$var reg 7 8 registro[6:0] $end
$upscope $end
$scope module rom1 $end
$var reg 1 9 clk $end
$var reg 7 : endereco[6:0] $end
$var reg 17 ; instr[16:0] $end
$upscope $end
$upscope $end
$upscope $end
$enddefinitions $end
#0
0!
0"
1#
bUUUUUUUUUUUUUUUUU $
0%
1&
bUUUUUUUUUUUUUUUUU '
b0000000 (
b0000000 )
0*
0+
bUUUUUUUUUUUUUUUUU ,
bUUUUUUUU -
0.
0/
10
01
02
03
14
05
b0000000 6
b0000000 7
b0000000 8
09
b0000000 :
bUUUUUUUUUUUUUUUUU ;
#50000000
1"
b00000011000010101 $
1%
b00000011000010101 '
b00000011000010101 ,
b00000011 -
1.
1/
13
19
b00000011000010101 ;
#100000000
0"
0%
0/
03
09
#150000000
1"
1%
1/
13
19
#200000000
0"
0#
0%
0&
0/
00
03
04
09
#250000000
1"
b00000000000000000 $
1%
b00000000000000000 '
b0010101 (
1*
1+
1/
11
12
13
15
b0010101 6
19
b0010101 :
#300000000
0"
0%
0/
03
09
#350000000
1"
b00000000000000100 $
1%
b00000000000000100 '
b0010101 )
0*
0+
b00000000000000100 ,
b00000000 -
0.
1/
01
02
13
05
b0010101 7
b0010101 8
19
b00000000000000100 ;
#400000000
0"
0%
0/
03
09
#450000000
1"
b00000000000000000 $
1%
b00000000000000000 '
b0010110 (
1*
1+
1/
11
12
13
15
b0010110 6
19
b0010110 :
#500000000
0"
0%
0/
03
09
#550000000
1"
b00000011000000010 $
1%
b00000011000000010 '
b0010110 )
0*
0+
b00000011000000010 ,
b00000011 -
1.
1/
01
02
13
05
b0010110 7
b0010110 8
19
b00000011000000010 ;
#600000000
0"
0%
0/
03
09
#650000000
1"
b00000000000000000 $
1%
b00000000000000000 '
b0000010 (
1*
1+
1/
11
12
13
15
b0000010 6
19
b0000010 :
#700000000
0"
0%
0/
03
09
#750000000
1"
b00000011000000110 $
1%
b00000011000000110 '
b0000010 )
0*
0+
b00000011000000110 ,
1/
01
02
13
05
b0000010 7
b0000010 8
19
b00000011000000110 ;
#800000000
0"
0%
0/
03
09
#850000000
1"
b00000000000000000 $
1%
b00000000000000000 '
b0000110 (
1*
1+
1/
11
12
13
15
b0000110 6
19
b0000110 :
#900000000
0"
0%
0/
03
09
#950000000
1"
b00000000000000001 $
1%
b00000000000000001 '
b0000110 )
0*
0+
b00000000000000001 ,
b00000000 -
0.
1/
01
02
13
05
b0000110 7
b0000110 8
19
b00000000000000001 ;
#1000000000
0"
0%
0/
03
09
#1050000000
1"
b00000000000000000 $
1%
b00000000000000000 '
b0000111 (
1*
1+
1/
11
12
13
15
b0000111 6
19
b0000111 :
#1100000000
0"
0%
0/
03
09
#1150000000
1"
b00000000000000111 $
1%
b00000000000000111 '
b0000111 )
0*
0+
b00000000000000111 ,
1/
01
02
13
05
b0000111 7
b0000111 8
19
b00000000000000111 ;
#1200000000
0"
0%
0/
03
09
#1250000000
1"
b00000000000000000 $
1%
b00000000000000000 '
b0001000 (
1*
1+
1/
11
12
13
15
b0001000 6
19
b0001000 :
#1300000000
0"
0%
0/
03
09
#1350000000
1"
1%
b0001000 )
0*
0+
b00000000000000000 ,
1/
01
02
13
05
b0001000 7
b0001000 8
19
b00000000000000000 ;
#1400000000
1!
0"
0%
0/
03
09
#1450000000
1"
1%
b0001001 (
1*
1+
1/
11
12
13
15
b0001001 6
19
b0001001 :
